Workbook

Sheet Instructions - Cash Runway
B2: Step-by-Step Instructions
B4: Steps | C4: Details
B5: 1 | C5: Open the “Inputs” sheet and set all model assumptions (blue cells)
B6: 2 | C6: Fill the “Headcount” plan — each role’s start date drives monthly payroll
B7: 3 | C7: Enter non-headcount costs and growth rates on the “Opex” sheet
B8: 4 | C8: Schedule equity, SAFE, note, and loan events on the “Financing” sheet
B9: 5 | C9: Review the “Cash Flow” model and the “Summary” dashboard for runway and burn
B12: What Each Input Means
B14: Metric | E14: Description
B15: Opening Cash Balance | E15: Cash on hand at the start of the model.
B16: Monthly Revenue Growth Rate | E16: Month-over-month growth applied to Month 1 revenue.
B17: Employer Payroll Burden % | E17: Taxes and benefits added on top of gross salaries.
B18: Avg Collection / Payables Days | E18: Timing lag between billing and cash, and between costs and payment.
B19: Headcount start dates | E19: When each hire begins; drives when their payroll hits cash flow.
B20: Financing close month | E20: When each round or loan lands as cash in the Cash Flow sheet.
B23: Important Guidelines
B25: Guideline | E25: Description
B26: Edit blue cells only | E26: Blue text is input; black is formula, green is a cross-sheet link — don’t overwrite.
B27: Watch yellow cells | E27: Yellow backgrounds flag key assumptions that need attention.
B28: Work left to right | E28: Set Inputs first; downstream sheets pull from those assumptions.
B29: Check the buffer | E29: The Cash Flow sheet flags months that fall below the minimum cash buffer.

Sheet Cover
B1: STARTUP CASH RUNWAY MODEL
B9: 1 INPUTS
B10: Set all model assumptions — opening cash, revenue growth, payroll burden, collection days, interest rates
B12: 2 HEADCOUNT
B13: Role-level hiring plan — every hire date drives monthly payroll using burden % from Inputs
B15: 3 OPEX
B16: Non-headcount operating costs — each line grows at its own rate from Inputs start date
B18: 4 FINANCING
B19: Schedule equity rounds, SAFEs, convertible notes & loans — cash hits Cash Flow on close date
B21: 5 CASH FLOW
B22: Consolidated model — inflows, outflows, net burn, ending cash, runway months & burn multiple
B24: 6 SUMMARY
... B36: ■ Yellow bg — Key assumption requiring attention

Sheet Inputs
B1: INPUTS — All blue cells are assumptions.
B3: GENERAL
B4: Model Start Month | C4: Jan-2026
B5: Number of Forecast Months | C5: 24
B6: Opening Cash Balance ($) | C6: 500000
B7: Currency | C7: INR
B9: REVENUE
B10: Month 1 Revenue ($) | C10: 75000
B11: Monthly Revenue Growth Rate | C11: 0.05
B12: Avg Collection Days | C12: 30
B13: Bad Debt Rate (%) | C13: 0.02
B15: PAYROLL
B16: Employer Payroll Burden % | C16: 0.15
B17: Annual Salary Increase % | C17: 0.08
B18: Payroll Pay Frequency | C18: Monthly
B20: PAYABLES & FINANCING
B21: Avg Payables Days | C21: 30
B22: Loan Interest Rate (Annual %) | C22: 0.08
B23: Min Cash Buffer ($) | C23: 50000

Sheet Headcount
B1: HEADCOUNT PLAN
B3: Department | C3: Role / Title | D3: Start Month | E3: End Month | F3: Annual Salary ($) | G3: No. of Personnnel | H3: Monthly Gross | I3: Monthly + Burden | J3: Jan-2026 | K3: Feb-2026 | L3: Mar-2026 | M3: Apr-2026 | N3: May-2026 | O3: Jun-2026 | P3: Jul-2026 | Q3: Aug-2026 | R3: Sep-2026 | S3: Oct-2026 | T3: Nov-2026 | U3: Dec-2026 | V3: Jan-2027 | W3: Feb-2027 | X3: Mar-2027 | Y3: Apr-2027 | Z3: May-2027 | AA3: Jun-2027 | AB3: Jul-2027 | AC3: Aug-2027 | AD3: Sep-2027 | AE3: Oct-2027 | AF3: Nov-2027 | AG3: Dec-2027
B5: Engineering | C5: CTO | D5: Jan-2026 | E5: — | F5: 120000 | G5: 1 | H5: =F5*G5/12 -> 10000 | I5: =H5*(1+Inputs!$C$16) -> 11500 | J5: =F5*G5/12*(1+Inputs!$C$16) -> 11500 | K5: =F5*G5/12*(1+Inputs!$C$16) -> 11500 | L5: =F5*G5/12*(1+Inputs!$C$16) -> 11500 | M5: =F5*G5/12*(1+Inputs!$C$16) -> 11500 | N5: =F5*G5/12*(1+Inputs!$C$16) -> 11500 | O5: =F5*G5/12*(1+Inputs!$C$16) -> 11500 | P5: =F5*G5/12*(1+Inputs!$C$16) -> 11500 | Q5: =F5*G5/12*(1+Inputs!$C$16) -> 11500 | R5: =F5*G5/12*(1+Inputs!$C$16) -> 11500 | S5: =F5*G5/12*(1+Inputs!$C$16) -> 11500 | T5: =F5*G5/12*(1+Inputs!$C$16) -> 11500 | U5: =F5*G5/12*(1+Inputs!$C$16) -> 11500 | V5: =F5*(1+Inputs!$C$17)*G5/12*(1+Inputs!$C$16) -> 12420 | W5: =F5*(1+Inputs!$C$17)*G5/12*(1+Inputs!$C$16) -> 12420 | X5: =F5*(1+Inputs!$C$17)*G5/12*(1+Inputs!$C$16) -> 12420 | Y5: =F5*(1+Inputs!$C$17)*G5/12*(1+Inputs!$C$16) -> 12420 | Z5: =F5*(1+Inputs!$C$17)*G5/12*(1+Inputs!$C$16) -> 12420 | AA5: =F5*(1+Inputs!$C$17)*G5/12*(1+Inputs!$C$16) -> 12420 | AB5: =F5*(1+Inputs!$C$17)*G5/12*(1+Inputs!$C$16) -> 12420 | AC5: =F5*(1+Inputs!$C$17)*G5/12*(1+Inputs!$C$16) -> 12420 | AD5: =F5*(1+Inputs!$C$17)*G5/12*(1+Inputs!$C$16) -> 12420 | AE5: =F5*(1+Inputs!$C$17)*G5/12*(1+Inputs!$C$16) -> 12420 | AF5: =F5*(1+Inputs!$C$17)*G5/12*(1+Inputs!$C$16) -> 12420 | AG5: =F5*(1+Inputs!$C$17)*G5/12*(1+Inputs!$C$16) -> 12420
B6: Engineering | C6: Senior Engineer | D6: Jan-2026 | E6: — | F6: 70000 | G6: 2 | H6: =F6*G6/12 -> 11666.667 | I6: =H6*(1+Inputs!$C$16) -> 13416.667 | J6: =F6*G6/12*(1+Inputs!$C$16) -> 13416.667 | K6: =F6*G6/12*(1+Inputs!$C$16) -> 13416.667 | L6: =F6*G6/12*(1+Inputs!$C$16) -> 13416.667 | M6: =F6*G6/12*(1+Inputs!$C$16) -> 13416.667 | N6: =F6*G6/12*(1+Inputs!$C$16) -> 13416.667 | O6: =F6*G6/12*(1+Inputs!$C$16) -> 13416.667 | P6: =F6*G6/12*(1+Inputs!$C$16) -> 13416.667 | Q6: =F6*G6/12*(1+Inputs!$C$16) -> 13416.667 | R6: =F6*G6/12*(1+Inputs!$C$16) -> 13416.667 | S6: =F6*G6/12*(1+Inputs!$C$16) -> 13416.667 | T6: =F6*G6/12*(1+Inputs!$C$16) -> 13416.667 | U6: =F6*G6/12*(1+Inputs!$C$16) -> 13416.667 | V6: =F6*(1+Inputs!$C$17)*G6/12*(1+Inputs!$C$16) -> 14490 | W6: =F6*(1+Inputs!$C$17)*G6/12*(1+Inputs!$C$16) -> 14490 | X6: =F6*(1+Inputs!$C$17)*G6/12*(1+Inputs!$C$16) -> 14490 | Y6: =F6*(1+Inputs!$C$17)*G6/12*(1+Inputs!$C$16) -> 14490 | Z6: =F6*(1+Inputs!$C$17)*G6/12*(1+Inputs!$C$16) -> 14490 | AA6: =F6*(1+Inputs!$C$17)*G6/12*(1+Inputs!$C$16) -> 14490 | AB6: =F6*(1+Inputs!$C$17)*G6/12*(1+Inputs!$C$16) -> 14490 | AC6: =F6*(1+Inputs!$C$17)*G6/12*(1+Inputs!$C$16) -> 14490 | AD6: =F6*(1+Inputs!$C$17)*G6/12*(1+Inputs!$C$16) -> 14490 | AE6: =F6*(1+Inputs!$C$17)*G6/12*(1+Inputs!$C$16) -> 14490 | AF6: =F6*(1+Inputs!$C$17)*G6/12*(1+Inputs!$C$16) -> 14490 | AG6: =F6*(1+Inputs!$C$17)*G6/12*(1+Inputs!$C$16) -> 14490
B7: Engineering | C7: Junior Engineer | D7: Apr-2026 | E7: — | F7: 50000 | G7: 1 | H7: =F7*G7/12 -> 4166.6667 | I7: =H7*(1+Inputs!$C$16) -> 4791.6667 | J7: 0 | K7: 0 | L7: 0 | M7: =F7*G7/12*(1+Inputs!$C$16) -> 4791.6667 | N7: =F7*G7/12*(1+Inputs!$C$16) -> 4791.6667 | O7: =F7*G7/12*(1+Inputs!$C$16) -> 4791.6667 | P7: =F7*G7/12*(1+Inputs!$C$16) -> 4791.6667 | Q7: =F7*G7/12*(1+Inputs!$C$16) -> 4791.6667 | R7: =F7*G7/12*(1+Inputs!$C$16) -> 4791.6667 | S7: =F7*G7/12*(1+Inputs!$C$16) -> 4791.6667 | T7: =F7*G7/12*(1+Inputs!$C$16) -> 4791.6667 | U7: =F7*G7/12*(1+Inputs!$C$16) -> 4791.6667 | V7: =F7*(1+Inputs!$C$17)*G7/12*(1+Inputs!$C$16) -> 5175 | W7: =F7*(1+Inputs!$C$17)*G7/12*(1+Inputs!$C$16) -> 5175 | X7: =F7*(1+Inputs!$C$17)*G7/12*(1+Inputs!$C$16) -> 5175 | Y7: =F7*(1+Inputs!$C$17)*G7/12*(1+Inputs!$C$16) -> 5175 | Z7: =F7*(1+Inputs!$C$17)*G7/12*(1+Inputs!$C$16) -> 5175 | AA7: =F7*(1+Inputs!$C$17)*G7/12*(1+Inputs!$C$16) -> 5175 | AB7: =F7*(1+Inputs!$C$17)*G7/12*(1+Inputs!$C$16) -> 5175 | AC7: =F7*(1+Inputs!$C$17)*G7/12*(1+Inputs!$C$16) -> 5175 | AD7: =F7*(1+Inputs!$C$17)*G7/12*(1+Inputs!$C$16) -> 5175 | AE7: =F7*(1+Inputs!$C$17)*G7/12*(1+Inputs!$C$16) -> 5175 | AF7: =F7*(1+Inputs!$C$17)*G7/12*(1+Inputs!$C$16) -> 5175 | AG7: =F7*(1+Inputs!$C$17)*G7/12*(1+Inputs!$C$16) -> 5175
B8: Product | C8: Head of Product | D8: Jan-2026 | E8: — | F8: 100000 | G8: 1 | H8: =F8*G8/12 -> 8333.3333 | I8: =H8*(1+Inputs!$C$16) -> 9583.3333 | J8: =F8*G8/12*(1+Inputs!$C$16) -> 9583.3333 | K8: =F8*G8/12*(1+Inputs!$C$16) -> 9583.3333 | L8: =F8*G8/12*(1+Inputs!$C$16) -> 9583.3333 | M8: =F8*G8/12*(1+Inputs!$C$16) -> 9583.3333 | N8: =F8*G8/12*(1+Inputs!$C$16) -> 9583.3333 | O8: =F8*G8/12*(1+Inputs!$C$16) -> 9583.3333 | P8: =F8*G8/12*(1+Inputs!$C$16) -> 9583.3333 | Q8: =F8*G8/12*(1+Inputs!$C$16) -> 9583.3333 | R8: =F8*G8/12*(1+Inputs!$C$16) -> 9583.3333 | S8: =F8*G8/12*(1+Inputs!$C$16) -> 9583.3333 | T8: =F8*G8/12*(1+Inputs!$C$16) -> 9583.3333 | U8: =F8*G8/12*(1+Inputs!$C$16) -> 9583.3333 | V8: =F8*(1+Inputs!$C$17)*G8/12*(1+Inputs!$C$16) -> 10350 | W8: =F8*(1+Inputs!$C$17)*G8/12*(1+Inputs!$C$16) -> 10350 | X8: =F8*(1+Inputs!$C$17)*G8/12*(1+Inputs!$C$16) -> 10350 | Y8: =F8*(1+Inputs!$C$17)*G8/12*(1+Inputs!$C$16) -> 10350 | Z8: =F8*(1+Inputs!$C$17)*G8/12*(1+Inputs!$C$16) -> 10350 | AA8: =F8*(1+Inputs!$C$17)*G8/12*(1+Inputs!$C$16) -> 10350 | AB8: =F8*(1+Inputs!$C$17)*G8/12*(1+Inputs!$C$16) -> 10350 | AC8: =F8*(1+Inputs!$C$17)*G8/12*(1+Inputs!$C$16) -> 10350 | AD8: =F8*(1+Inputs!$C$17)*G8/12*(1+Inputs!$C$16) -> 10350 | AE8: =F8*(1+Inputs!$C$17)*G8/12*(1+Inputs!$C$16) -> 10350 | AF8: =F8*(1+Inputs!$C$17)*G8/12*(1+Inputs!$C$16) -> 10350 | AG8: =F8*(1+Inputs!$C$17)*G8/12*(1+Inputs!$C$16) -> 10350
B9: Product | C9: Product Manager | D9: Jun-2026 | E9: — | F9: 90000 | G9: 1 | H9: =F9*G9/12 -> 7500 | I9: =H9*(1+Inputs!$C$16) -> 8625 | J9: 0 | K9: 0 | L9: 0 | M9: 0 | N9: 0 | O9: =F9*G9/12*(1+Inputs!$C$16) -> 8625 | P9: =F9*G9/12*(1+Inputs!$C$16) -> 8625 | Q9: =F9*G9/12*(1+Inputs!$C$16) -> 8625 | R9: =F9*G9/12*(1+Inputs!$C$16) -> 8625 | S9: =F9*G9/12*(1+Inputs!$C$16) -> 8625 | T9: =F9*G9/12*(1+Inputs!$C$16) -> 8625 | U9: =F9*G9/12*(1+Inputs!$C$16) -> 8625 | V9: =F9*(1+Inputs!$C$17)*G9/12*(1+Inputs!$C$16) -> 9315 | W9: =F9*(1+Inputs!$C$17)*G9/12*(1+Inputs!$C$16) -> 9315 | X9: =F9*(1+Inputs!$C$17)*G9/12*(1+Inputs!$C$16) -> 9315 | Y9: =F9*(1+Inputs!$C$17)*G9/12*(1+Inputs!$C$16) -> 9315 | Z9: =F9*(1+Inputs!$C$17)*G9/12*(1+Inputs!$C$16) -> 9315 | AA9: =F9*(1+Inputs!$C$17)*G9/12*(1+Inputs!$C$16) -> 9315 | AB9: =F9*(1+Inputs!$C$17)*G9/12*(1+Inputs!$C$16) -> 9315 | AC9: =F9*(1+Inputs!$C$17)*G9/12*(1+Inputs!$C$16) -> 9315 | AD9: =F9*(1+Inputs!$C$17)*G9/12*(1+Inputs!$C$16) -> 9315 | AE9: =F9*(1+Inputs!$C$17)*G9/12*(1+Inputs!$C$16) -> 9315 | AF9: =F9*(1+Inputs!$C$17)*G9/12*(1+Inputs!$C$16) -> 9315 | AG9: =F9*(1+Inputs!$C$17)*G9/12*(1+Inputs!$C$16) -> 9315
B10: Sales | C10: VP of Sales | D10: Jan-2026 | E10: — | F10: 110000 | G10: 1 | H10: =F10*G10/12 -> 9166.6667 | I10: =H10*(1+Inputs!$C$16) -> 10541.667 | J10: =F10*G10/12*(1+Inputs!$C$16) -> 10541.667 | K10: =F10*G10/12*(1+Inputs!$C$16) -> 10541.667 | L10: =F10*G10/12*(1+Inputs!$C$16) -> 10541.667 | M10: =F10*G10/12*(1+Inputs!$C$16) -> 10541.667 | N10: =F10*G10/12*(1+Inputs!$C$16) -> 10541.667 | O10: =F10*G10/12*(1+Inputs!$C$16) -> 10541.667 | P10: =F10*G10/12*(1+Inputs!$C$16) -> 10541.667 | Q10: =F10*G10/12*(1+Inputs!$C$16) -> 10541.667 | R10: =F10*G10/12*(1+Inputs!$C$16) -> 10541.667 | S10: =F10*G10/12*(1+Inputs!$C$16) -> 10541.667 | T10: =F10*G10/12*(1+Inputs!$C$16) -> 10541.667 | U10: =F10*G10/12*(1+Inputs!$C$16) -> 10541.667 | V10: =F10*(1+Inputs!$C$17)*G10/12*(1+Inputs!$C$16) -> 11385 | W10: =F10*(1+Inputs!$C$17)*G10/12*(1+Inputs!$C$16) -> 11385 | X10: =F10*(1+Inputs!$C$17)*G10/12*(1+Inputs!$C$16) -> 11385 | Y10: =F10*(1+Inputs!$C$17)*G10/12*(1+Inputs!$C$16) -> 11385 | Z10: =F10*(1+Inputs!$C$17)*G10/12*(1+Inputs!$C$16) -> 11385 | AA10: =F10*(1+Inputs!$C$17)*G10/12*(1+Inputs!$C$16) -> 11385 | AB10: =F10*(1+Inputs!$C$17)*G10/12*(1+Inputs!$C$16) -> 11385 | AC10: =F10*(1+Inputs!$C$17)*G10/12*(1+Inputs!$C$16) -> 11385 | AD10: =F10*(1+Inputs!$C$17)*G10/12*(1+Inputs!$C$16) -> 11385 | AE10: =F10*(1+Inputs!$C$17)*G10/12*(1+Inputs!$C$16) -> 11385 | AF10: =F10*(1+Inputs!$C$17)*G10/12*(1+Inputs!$C$16) -> 11385 | AG10: =F10*(1+Inputs!$C$17)*G10/12*(1+Inputs!$C$16) -> 11385
B11: Sales | C11: Account Executive | D11: Mar-2026 | E11: — | F11: 75000 | G11: 2 | H11: =F11*G11/12 -> 12500 | I11: =H11*(1+Inputs!$C$16) -> 14375 | J11: 0 | K11: 0 | L11: =F11*G11/12*(1+Inputs!$C$16) -> 14375 | M11: =F11*G11/12*(1+Inputs!$C$16) -> 14375 | N11: =F11*G11/12*(1+Inputs!$C$16) -> 14375 | O11: =F11*G11/12*(1+Inputs!$C$16) -> 14375 | P11: =F11*G11/12*(1+Inputs!$C$16) -> 14375 | Q11: =F11*G11/12*(1+Inputs!$C$16) -> 14375 | R11: =F11*G11/12*(1+Inputs!$C$16) -> 14375 | S11: =F11*G11/12*(1+Inputs!$C$16) -> 14375 | T11: =F11*G11/12*(1+Inputs!$C$16) -> 14375 | U11: =F11*G11/12*(1+Inputs!$C$16) -> 14375 | V11: =F11*(1+Inputs!$C$17)*G11/12*(1+Inputs!$C$16) -> 15525 | W11: =F11*(1+Inputs!$C$17)*G11/12*(1+Inputs!$C$16) -> 15525 | X11: =F11*(1+Inputs!$C$17)*G11/12*(1+Inputs!$C$16) -> 15525 | Y11: =F11*(1+Inputs!$C$17)*G11/12*(1+Inputs!$C$16) -> 15525 | Z11: =F11*(1+Inputs!$C$17)*G11/12*(1+Inputs!$C$16) -> 15525 | AA11: =F11*(1+Inputs!$C$17)*G11/12*(1+Inputs!$C$16) -> 15525 | AB11: =F11*(1+Inputs!$C$17)*G11/12*(1+Inputs!$C$16) -> 15525 | AC11: =F11*(1+Inputs!$C$17)*G11/12*(1+Inputs!$C$16) -> 15525 | AD11: =F11*(1+Inputs!$C$17)*G11/12*(1+Inputs!$C$16) -> 15525 | AE11: =F11*(1+Inputs!$C$17)*G11/12*(1+Inputs!$C$16) -> 15525 | AF11: =F11*(1+Inputs!$C$17)*G11/12*(1+Inputs!$C$16) -> 15525 | AG11: =F11*(1+Inputs!$C$17)*G11/12*(1+Inputs!$C$16) -> 15525
B12: Marketing | C12: Growth Lead | D12: Feb-2026 | E12: — | F12: 90000 | G12: 1 | H12: =F12*G12/12 -> 7500 | I12: =H12*(1+Inputs!$C$16) -> 8625 | J12: 0 | K12: =F12*G12/12*(1+Inputs!$C$16) -> 8625 | L12: =F12*G12/12*(1+Inputs!$C$16) -> 8625 | M12: =F12*G12/12*(1+Inputs!$C$16) -> 8625 | N12: =F12*G12/12*(1+Inputs!$C$16) -> 8625 | O12: =F12*G12/12*(1+Inputs!$C$16) -> 8625 | P12: =F12*G12/12*(1+Inputs!$C$16) -> 8625 | Q12: =F12*G12/12*(1+Inputs!$C$16) -> 8625 | R12: =F12*G12/12*(1+Inputs!$C$16) -> 8625 | S12: =F12*G12/12*(1+Inputs!$C$16) -> 8625 | T12: =F12*G12/12*(1+Inputs!$C$16) -> 8625 | U12: =F12*G12/12*(1+Inputs!$C$16) -> 8625 | V12: =F12*(1+Inputs!$C$17)*G12/12*(1+Inputs!$C$16) -> 9315 | W12: =F12*(1+Inputs!$C$17)*G12/12*(1+Inputs!$C$16) -> 9315 | X12: =F12*(1+Inputs!$C$17)*G12/12*(1+Inputs!$C$16) -> 9315 | Y12: =F12*(1+Inputs!$C$17)*G12/12*(1+Inputs!$C$16) -> 9315 | Z12: =F12*(1+Inputs!$C$17)*G12/12*(1+Inputs!$C$16) -> 9315 | AA12: =F12*(1+Inputs!$C$17)*G12/12*(1+Inputs!$C$16) -> 9315 | AB12: =F12*(1+Inputs!$C$17)*G12/12*(1+Inputs!$C$16) -> 9315 | AC12: =F12*(1+Inputs!$C$17)*G12/12*(1+Inputs!$C$16) -> 9315 | AD12: =F12*(1+Inputs!$C$17)*G12/12*(1+Inputs!$C$16) -> 9315 | AE12: =F12*(1+Inputs!$C$17)*G12/12*(1+Inputs!$C$16) -> 9315 | AF12: =F12*(1+Inputs!$C$17)*G12/12*(1+Inputs!$C$16) -> 9315 | AG12: =F12*(1+Inputs!$C$17)*G12/12*(1+Inputs!$C$16) -> 9315
B13: G&A | C13: CEO | D13: Jan-2026 | E13: — | F13: 150000 | G13: 1 | H13: =F13*G13/12 -> 12500 | I13: =H13*(1+Inputs!$C$16) -> 14375 | J13: =F13*G13/12*(1+Inputs!$C$16) -> 14375 | K13: =F13*G13/12*(1+Inputs!$C$16) -> 14375 | L13: =F13*G13/12*(1+Inputs!$C$16) -> 14375 | M13: =F13*G13/12*(1+Inputs!$C$16) -> 14375 | N13: =F13*G13/12*(1+Inputs!$C$16) -> 14375 | O13: =F13*G13/12*(1+Inputs!$C$16) -> 14375 | P13: =F13*G13/12*(1+Inputs!$C$16) -> 14375 | Q13: =F13*G13/12*(1+Inputs!$C$16) -> 14375 | R13: =F13*G13/12*(1+Inputs!$C$16) -> 14375 | S13: =F13*G13/12*(1+Inputs!$C$16) -> 14375 | T13: =F13*G13/12*(1+Inputs!$C$16) -> 14375 | U13: =F13*G13/12*(1+Inputs!$C$16) -> 14375 | V13: =F13*(1+Inputs!$C$17)*G13/12*(1+Inputs!$C$16) -> 15525 | W13: =F13*(1+Inputs!$C$17)*G13/12*(1+Inputs!$C$16) -> 15525 | X13: =F13*(1+Inputs!$C$17)*G13/12*(1+Inputs!$C$16) -> 15525 | Y13: =F13*(1+Inputs!$C$17)*G13/12*(1+Inputs!$C$16) -> 15525 | Z13: =F13*(1+Inputs!$C$17)*G13/12*(1+Inputs!$C$16) -> 15525 | AA13: =F13*(1+Inputs!$C$17)*G13/12*(1+Inputs!$C$16) -> 15525 | AB13: =F13*(1+Inputs!$C$17)*G13/12*(1+Inputs!$C$16) -> 15525 | AC13: =F13*(1+Inputs!$C$17)*G13/12*(1+Inputs!$C$16) -> 15525 | AD13: =F13*(1+Inputs!$C$17)*G13/12*(1+Inputs!$C$16) -> 15525 | AE13: =F13*(1+Inputs!$C$17)*G13/12*(1+Inputs!$C$16) -> 15525 | AF13: =F13*(1+Inputs!$C$17)*G13/12*(1+Inputs!$C$16) -> 15525 | AG13: =F13*(1+Inputs!$C$17)*G13/12*(1+Inputs!$C$16) -> 15525
B14: G&A | C14: Finance Manager | D14: Jul-2026 | E14: — | F14: 90000 | G14: 1 | H14: =F14*G14/12 -> 7500 | I14: =H14*(1+Inputs!$C$16) -> 8625 | J14: 0 | K14: 0 | L14: 0 | M14: 0 | N14: 0 | O14: 0 | P14: =F14*G14/12*(1+Inputs!$C$16) -> 8625 | Q14: =F14*G14/12*(1+Inputs!$C$16) -> 8625 | R14: =F14*G14/12*(1+Inputs!$C$16) -> 8625 | S14: =F14*G14/12*(1+Inputs!$C$16) -> 8625 | T14: =F14*G14/12*(1+Inputs!$C$16) -> 8625 | U14: =F14*G14/12*(1+Inputs!$C$16) -> 8625 | V14: =F14*(1+Inputs!$C$17)*G14/12*(1+Inputs!$C$16) -> 9315 | W14: =F14*(1+Inputs!$C$17)*G14/12*(1+Inputs!$C$16) -> 9315 | X14: =F14*(1+Inputs!$C$17)*G14/12*(1+Inputs!$C$16) -> 9315 | Y14: =F14*(1+Inputs!$C$17)*G14/12*(1+Inputs!$C$16) -> 9315 | Z14: =F14*(1+Inputs!$C$17)*G14/12*(1+Inputs!$C$16) -> 9315 | AA14: =F14*(1+Inputs!$C$17)*G14/12*(1+Inputs!$C$16) -> 9315 | AB14: =F14*(1+Inputs!$C$17)*G14/12*(1+Inputs!$C$16) -> 9315 | AC14: =F14*(1+Inputs!$C$17)*G14/12*(1+Inputs!$C$16) -> 9315 | AD14: =F14*(1+Inputs!$C$17)*G14/12*(1+Inputs!$C$16) -> 9315 | AE14: =F14*(1+Inputs!$C$17)*G14/12*(1+Inputs!$C$16) -> 9315 | AF14: =F14*(1+Inputs!$C$17)*G14/12*(1+Inputs!$C$16) -> 9315 | AG14: =F14*(1+Inputs!$C$17)*G14/12*(1+Inputs!$C$16) -> 9315
B16: Subtotal — Engineering | J16: =SUM(J5,J6,J7) -> 24916.667 | K16: =SUM(K5,K6,K7) -> 24916.667 | L16: =SUM(L5,L6,L7) -> 24916.667 | M16: =SUM(M5,M6,M7) -> 29708.333 | N16: =SUM(N5,N6,N7) -> 29708.333 | O16: =SUM(O5,O6,O7) -> 29708.333 | P16: =SUM(P5,P6,P7) -> 29708.333 | Q16: =SUM(Q5,Q6,Q7) -> 29708.333 | ... AG16: =SUM(AG5,AG6,AG7) -> 32085
B17: Subtotal — Product | J17: =SUM(J8,J9) -> 9583.3333 | K17: =SUM(K8,K9) -> 9583.3333 | L17: =SUM(L8,L9) -> 9583.3333 | M17: =SUM(M8,M9) -> 9583.3333 | N17: =SUM(N8,N9) -> 9583.3333 | O17: =SUM(O8,O9) -> 18208.333 | P17: =SUM(P8,P9) -> 18208.333 | Q17: =SUM(Q8,Q9) -> 18208.333 | ... AG17: =SUM(AG8,AG9) -> 19665
B18: Subtotal — Sales | J18: =SUM(J10,J11) -> 10541.667 | K18: =SUM(K10,K11) -> 10541.667 | L18: =SUM(L10,L11) -> 24916.667 | M18: =SUM(M10,M11) -> 24916.667 | N18: =SUM(N10,N11) -> 24916.667 | O18: =SUM(O10,O11) -> 24916.667 | P18: =SUM(P10,P11) -> 24916.667 | Q18: =SUM(Q10,Q11) -> 24916.667 | ... AG18: =SUM(AG10,AG11) -> 26910
B19: Subtotal — Marketing | J19: =SUM(J12) -> 0 | K19: =SUM(K12) -> 8625 | L19: =SUM(L12) -> 8625 | M19: =SUM(M12) -> 8625 | N19: =SUM(N12) -> 8625 | O19: =SUM(O12) -> 8625 | P19: =SUM(P12) -> 8625 | Q19: =SUM(Q12) -> 8625 | ... AG19: =SUM(AG12) -> 9315
B20: Subtotal — G&A | J20: =SUM(J13,J14) -> 14375 | K20: =SUM(K13,K14) -> 14375 | L20: =SUM(L13,L14) -> 14375 | M20: =SUM(M13,M14) -> 14375 | N20: =SUM(N13,N14) -> 14375 | O20: =SUM(O13,O14) -> 14375 | P20: =SUM(P13,P14) -> 23000 | Q20: =SUM(Q13,Q14) -> 23000 | ... AG20: =SUM(AG13,AG14) -> 24840
B22: TOTAL MONTHLY PAYROLL (incl. burden) | J22: =SUM(J16,J17,J18,J19,J20) -> 59416.667 | K22: =SUM(K16,K17,K18,K19,K20) -> 68041.667 | L22: =SUM(L16,L17,L18,L19,L20) -> 82416.667 | M22: =SUM(M16,M17,M18,M19,M20) -> 87208.333 | N22: =SUM(N16,N17,N18,N19,N20) -> 87208.333 | O22: =SUM(O16,O17,O18,O19,O20) -> 95833.333 | P22: =SUM(P16,P17,P18,P19,P20) -> 104458.33 | Q22: =SUM(Q16,Q17,Q18,Q19,Q20) -> 104458.33 | ... AG22: =SUM(AG16,AG17,AG18,AG19,AG20) -> 112815

Sheet Opex
B1: OPERATING EXPENSES (Non-Headcount)
B3: Category | C3: Description | D3: Month 1 Cost ($) | E3: MoM Growth (%) | F3: Jan-2026 | G3: Feb-2026 | H3: Mar-2026 | I3: Apr-2026 | J3: May-2026 | K3: Jun-2026 | L3: Jul-2026 | M3: Aug-2026 | N3: Sep-2026 | O3: Oct-2026 | P3: Nov-2026 | Q3: Dec-2026 | R3: Jan-2027 | S3: Feb-2027 | T3: Mar-2027 | U3: Apr-2027 | V3: May-2027 | W3: Jun-2027 | X3: Jul-2027 | Y3: Aug-2027 | Z3: Sep-2027 | AA3: Oct-2027 | AB3: Nov-2027 | AC3: Dec-2027
B5: Infrastructure | C5: Cloud / AWS / GCP | D5: 8000 | E5: 0.03 | F5: =D5 -> 8000 | G5: =F5*(1+$E$5) -> 8240 | H5: =G5*(1+$E$5) -> 8487.2 | I5: =H5*(1+$E$5) -> 8741.816 | J5: =I5*(1+$E$5) -> 9004.0705 | K5: =J5*(1+$E$5) -> 9274.1926 | L5: =K5*(1+$E$5) -> 9552.4184 | M5: =L5*(1+$E$5) -> 9838.9909 | N5: =M5*(1+$E$5) -> 10134.161 | ... AC5: =AB5*(1+$E$5) -> 15788.692
B6: Infrastructure | C6: SaaS Tools & Licenses | D6: 3500 | E6: 0.02 | F6: =D6 -> 3500 | G6: =F6*(1+$E$6) -> 3570 | H6: =G6*(1+$E$6) -> 3641.4 | I6: =H6*(1+$E$6) -> 3714.228 | J6: =I6*(1+$E$6) -> 3788.5126 | K6: =J6*(1+$E$6) -> 3864.2828 | L6: =K6*(1+$E$6) -> 3941.5685 | M6: =L6*(1+$E$6) -> 4020.3998 | N6: =M6*(1+$E$6) -> 4100.8078 | ... AC6: =AB6*(1+$E$6) -> 5519.1474
B7: Marketing | C7: Paid Ads / Acquisition | D7: 7000 | E7: 0.05 | F7: =D7 -> 7000 | G7: =F7*(1+$E$7) -> 7350 | H7: =G7*(1+$E$7) -> 7717.5 | I7: =H7*(1+$E$7) -> 8103.375 | J7: =I7*(1+$E$7) -> 8508.5438 | K7: =J7*(1+$E$7) -> 8933.9709 | L7: =K7*(1+$E$7) -> 9380.6695 | M7: =L7*(1+$E$7) -> 9849.703 | N7: =M7*(1+$E$7) -> 10342.188 | ... AC7: =AB7*(1+$E$7) -> 21500.666
B8: Marketing | C8: Events & Conferences | D8: 1500 | E8: 0.01 | F8: =D8 -> 1500 | G8: =F8*(1+$E$8) -> 1515 | H8: =G8*(1+$E$8) -> 1530.15 | I8: =H8*(1+$E$8) -> 1545.4515 | J8: =I8*(1+$E$8) -> 1560.906 | K8: =J8*(1+$E$8) -> 1576.5151 | L8: =K8*(1+$E$8) -> 1592.2802 | M8: =L8*(1+$E$8) -> 1608.203 | N8: =M8*(1+$E$8) -> 1624.2851 | ... AC8: =AB8*(1+$E$8) -> 1885.7445
B9: Occupancy | C9: Office Rent | D9: 5000 | E9: 0 | F9: =D9 -> 5000 | G9: =F9*(1+$E$9) -> 5000 | H9: =G9*(1+$E$9) -> 5000 | I9: =H9*(1+$E$9) -> 5000 | J9: =I9*(1+$E$9) -> 5000 | K9: =J9*(1+$E$9) -> 5000 | L9: =K9*(1+$E$9) -> 5000 | M9: =L9*(1+$E$9) -> 5000 | N9: =M9*(1+$E$9) -> 5000 | ... AC9: =AB9*(1+$E$9) -> 5000
B10: Occupancy | C10: Utilities & Supplies | D10: 800 | E10: 0.01 | F10: =D10 -> 800 | G10: =F10*(1+$E$10) -> 808 | H10: =G10*(1+$E$10) -> 816.08 | I10: =H10*(1+$E$10) -> 824.2408 | J10: =I10*(1+$E$10) -> 832.48321 | K10: =J10*(1+$E$10) -> 840.80804 | L10: =K10*(1+$E$10) -> 849.21612 | M10: =L10*(1+$E$10) -> 857.70828 | N10: =M10*(1+$E$10) -> 866.28536 | ... AC10: =AB10*(1+$E$10) -> 1005.7304
B11: Professional | C11: Legal & Compliance | D11: 3000 | E11: 0 | F11: =D11 -> 3000 | G11: =F11*(1+$E$11) -> 3000 | H11: =G11*(1+$E$11) -> 3000 | I11: =H11*(1+$E$11) -> 3000 | J11: =I11*(1+$E$11) -> 3000 | K11: =J11*(1+$E$11) -> 3000 | L11: =K11*(1+$E$11) -> 3000 | M11: =L11*(1+$E$11) -> 3000 | N11: =M11*(1+$E$11) -> 3000 | ... AC11: =AB11*(1+$E$11) -> 3000
B12: Professional | C12: Accounting / Audit | D12: 2000 | E12: 0 | F12: =D12 -> 2000 | G12: =F12*(1+$E$12) -> 2000 | H12: =G12*(1+$E$12) -> 2000 | I12: =H12*(1+$E$12) -> 2000 | J12: =I12*(1+$E$12) -> 2000 | K12: =J12*(1+$E$12) -> 2000 | L12: =K12*(1+$E$12) -> 2000 | M12: =L12*(1+$E$12) -> 2000 | N12: =M12*(1+$E$12) -> 2000 | ... AC12: =AB12*(1+$E$12) -> 2000
B13: T&E | C13: Travel & Entertainment | D13: 2500 | E13: 0.01 | F13: =D13 -> 2500 | G13: =F13*(1+$E$13) -> 2525 | H13: =G13*(1+$E$13) -> 2550.25 | I13: =H13*(1+$E$13) -> 2575.7525 | J13: =I13*(1+$E$13) -> 2601.51 | K13: =J13*(1+$E$13) -> 2627.5251 | L13: =K13*(1+$E$13) -> 2653.8004 | M13: =L13*(1+$E$13) -> 2680.3384 | N13: =M13*(1+$E$13) -> 2707.1418 | ... AC13: =AB13*(1+$E$13) -> 3142.9075
B14: Other | C14: Miscellaneous | D14: 1000 | E14: 0.01 | F14: =D14 -> 1000 | G14: =F14*(1+$E$14) -> 1010 | H14: =G14*(1+$E$14) -> 1020.1 | I14: =H14*(1+$E$14) -> 1030.301 | J14: =I14*(1+$E$14) -> 1040.604 | K14: =J14*(1+$E$14) -> 1051.0101 | L14: =K14*(1+$E$14) -> 1061.5202 | M14: =L14*(1+$E$14) -> 1072.1354 | N14: =M14*(1+$E$14) -> 1082.8567 | ... AC14: =AB14*(1+$E$14) -> 1257.163
B16: Subtotal — Infrastructure | F16: =SUM(F5,F6) -> 11500 | G16: =SUM(G5,G6) -> 11810 | H16: =SUM(H5,H6) -> 12128.6 | I16: =SUM(I5,I6) -> 12456.044 | J16: =SUM(J5,J6) -> 12792.583 | K16: =SUM(K5,K6) -> 13138.475 | L16: =SUM(L5,L6) -> 13493.987 | M16: =SUM(M5,M6) -> 13859.391 | ... AC16: =SUM(AC5,AC6) -> 21307.84
B17: Subtotal — Marketing | F17: =SUM(F7,F8) -> 8500 | G17: =SUM(G7,G8) -> 8865 | H17: =SUM(H7,H8) -> 9247.65 | I17: =SUM(I7,I8) -> 9648.8265 | J17: =SUM(J7,J8) -> 10069.45 | K17: =SUM(K7,K8) -> 10510.486 | L17: =SUM(L7,L8) -> 10972.95 | M17: =SUM(M7,M8) -> 11457.906 | ... AC17: =SUM(AC7,AC8) -> 23386.411
B18: Subtotal — Occupancy | F18: =SUM(F9,F10) -> 5800 | G18: =SUM(G9,G10) -> 5808 | H18: =SUM(H9,H10) -> 5816.08 | I18: =SUM(I9,I10) -> 5824.2408 | J18: =SUM(J9,J10) -> 5832.4832 | K18: =SUM(K9,K10) -> 5840.808 | L18: =SUM(L9,L10) -> 5849.2161 | M18: =SUM(M9,M10) -> 5857.7083 | ... AC18: =SUM(AC9,AC10) -> 6005.7304
B19: Subtotal — Professional | F19: =SUM(F11,F12) -> 5000 | G19: =SUM(G11,G12) -> 5000 | H19: =SUM(H11,H12) -> 5000 | I19: =SUM(I11,I12) -> 5000 | J19: =SUM(J11,J12) -> 5000 | K19: =SUM(K11,K12) -> 5000 | L19: =SUM(L11,L12) -> 5000 | M19: =SUM(M11,M12) -> 5000 | ... AC19: =SUM(AC11,AC12) -> 5000
B20: Subtotal — T&E | F20: =SUM(F13) -> 2500 | G20: =SUM(G13) -> 2525 | H20: =SUM(H13) -> 2550.25 | I20: =SUM(I13) -> 2575.7525 | J20: =SUM(J13) -> 2601.51 | K20: =SUM(K13) -> 2627.5251 | L20: =SUM(L13) -> 2653.8004 | M20: =SUM(M13) -> 2680.3384 | ... AC20: =SUM(AC13) -> 3142.9075
B21: Subtotal — Other | F21: =SUM(F14) -> 1000 | G21: =SUM(G14) -> 1010 | H21: =SUM(H14) -> 1020.1 | I21: =SUM(I14) -> 1030.301 | J21: =SUM(J14) -> 1040.604 | K21: =SUM(K14) -> 1051.0101 | L21: =SUM(L14) -> 1061.5202 | M21: =SUM(M14) -> 1072.1354 | ... AC21: =SUM(AC14) -> 1257.163
B23: TOTAL MONTHLY OPEX | F23: =SUM(F16,F17,F18,F19,F20,F21) -> 34300 | G23: =SUM(G16,G17,G18,G19,G20,G21) -> 35018 | H23: =SUM(H16,H17,H18,H19,H20,H21) -> 35762.68 | I23: =SUM(I16,I17,I18,I19,I20,I21) -> 36535.165 | J23: =SUM(J16,J17,J18,J19,J20,J21) -> 37336.63 | K23: =SUM(K16,K17,K18,K19,K20,K21) -> 38168.305 | L23: =SUM(L16,L17,L18,L19,L20,L21) -> 39031.473 | M23: =SUM(M16,M17,M18,M19,M20,M21) -> 39927.479 | ... AC23: =SUM(AC16,AC17,AC18,AC19,AC20,AC21) -> 60100.051

Sheet Financing
B1: FINANCING EVENTS
B3: Event Name | C3: Type | D3: Close Month | E3: Gross Amount ($) | F3: Fees / Costs ($) | G3: Net Cash In ($) | H3: Notes | I3: Jan-2026 | J3: Feb-2026 | K3: Mar-2026 | L3: Apr-2026 | M3: May-2026 | N3: Jun-2026 | O3: Jul-2026 | P3: Aug-2026 | Q3: Sep-2026 | R3: Oct-2026 | S3: Nov-2026 | T3: Dec-2026 | U3: Jan-2027 | V3: Feb-2027 | W3: Mar-2027 | X3: Apr-2027 | Y3: May-2027 | Z3: Jun-2027 | AA3: Jul-2027 | AB3: Aug-2027 | AC3: Sep-2027 | AD3: Oct-2027 | AE3: Nov-2027 | AF3: Dec-2027
B5: Seed Round | C5: Equity | D5: Jan-2026 | E5: 1000000 | F5: 75000 | G5: =E5-F5 -> 925000 | I5: =G5 -> 925000 | J5: 0 | K5: 0 | L5: 0 | M5: 0 | N5: 0 | O5: 0 | P5: 0 | Q5: 0 | R5: 0 | S5: 0 | T5: 0 | U5: 0 | V5: 0 | W5: 0 | X5: 0 | Y5: 0 | Z5: 0 | AA5: 0 | AB5: 0 | AC5: 0 | AD5: 0 | AE5: 0 | AF5: 0
B6: Bank Loan | C6: Loan | D6: Mar-2026 | E6: 150000 | F6: 12000 | G6: =E6-F6 -> 138000 | I6: 0 | J6: 0 | K6: =G6 -> 138000 | L6: 0 | M6: 0 | N6: 0 | O6: 0 | P6: 0 | Q6: 0 | R6: 0 | S6: 0 | T6: 0 | U6: 0 | V6: 0 | W6: 0 | X6: 0 | Y6: 0 | Z6: 0 | AA6: 0 | AB6: 0 | AC6: 0 | AD6: 0 | AE6: 0 | AF6: 0
B7: Convertible Note | C7: Convertible Note | D7: Jun-2026 | E7: 250000 | F7: 15000 | G7: =E7-F7 -> 235000 | I7: 0 | J7: 0 | K7: 0 | L7: 0 | M7: 0 | N7: =G7 -> 235000 | O7: 0 | P7: 0 | Q7: 0 | R7: 0 | S7: 0 | T7: 0 | U7: 0 | V7: 0 | W7: 0 | X7: 0 | Y7: 0 | Z7: 0 | AA7: 0 | AB7: 0 | AC7: 0 | AD7: 0 | AE7: 0 | AF7: 0
B8: Series A | C8: Equity | D8: Jan-2027 | E8: 3000000 | F8: 250000 | G8: =E8-F8 -> 2750000 | I8: 0 | J8: 0 | K8: 0 | L8: 0 | M8: 0 | N8: 0 | O8: 0 | P8: 0 | Q8: 0 | R8: 0 | S8: 0 | T8: 0 | U8: =G8 -> 2750000 | V8: 0 | W8: 0 | X8: 0 | Y8: 0 | Z8: 0 | AA8: 0 | AB8: 0 | AC8: 0 | AD8: 0 | AE8: 0 | AF8: 0
B10: TOTAL FINANCING INFLOWS | I10: =SUM(I5:I8) -> 925000 | J10: =SUM(J5:J8) -> 0 | K10: =SUM(K5:K8) -> 138000 | L10: =SUM(L5:L8) -> 0 | M10: =SUM(M5:M8) -> 0 | N10: =SUM(N5:N8) -> 235000 | O10: =SUM(O5:O8) -> 0 | P10: =SUM(P5:P8) -> 0 | ... AF10: =SUM(AF5:AF8) -> 0

Sheet Cash Flow
B1: CASH FLOW MODEL
B3: LINE ITEM | C3: Jan-2026 | D3: Feb-2026 | E3: Mar-2026 | F3: Apr-2026 | G3: May-2026 | H3: Jun-2026 | I3: Jul-2026 | J3: Aug-2026 | K3: Sep-2026 | L3: Oct-2026 | M3: Nov-2026 | N3: Dec-2026 | O3: Jan-2027 | P3: Feb-2027 | Q3: Mar-2027 | R3: Apr-2027 | S3: May-2027 | T3: Jun-2027 | U3: Jul-2027 | V3: Aug-2027 | W3: Sep-2027 | X3: Oct-2027 | Y3: Nov-2027 | Z3: Dec-2027
B5: CASH INFLOWS
B6: Revenue (MRR) ($) | C6: =Inputs!$C$10 -> 75000 | D6: =C6*(1+Inputs!$C$11) -> 78750 | E6: =D6*(1+Inputs!$C$11) -> 82687.5 | F6: =E6*(1+Inputs!$C$11) -> 86821.875 | G6: =F6*(1+Inputs!$C$11) -> 91162.969 | H6: =G6*(1+Inputs!$C$11) -> 95721.117 | I6: =H6*(1+Inputs!$C$11) -> 100507.17 | J6: =I6*(1+Inputs!$C$11) -> 105532.53 | K6: =J6*(1+Inputs!$C$11) -> 110809.16 | ... Z6: =Y6*(1+Inputs!$C$11) -> 230364.28
B7: Cash Collections ($) | C7: 0 | D7: =C6*(1-Inputs!$C$13) -> 73500 | E7: =D6*(1-Inputs!$C$13) -> 77175 | F7: =E6*(1-Inputs!$C$13) -> 81033.75 | G7: =F6*(1-Inputs!$C$13) -> 85085.438 | H7: =G6*(1-Inputs!$C$13) -> 89339.709 | I7: =H6*(1-Inputs!$C$13) -> 93806.695 | J7: =I6*(1-Inputs!$C$13) -> 98497.03 | K7: =J6*(1-Inputs!$C$13) -> 103421.88 | ... Z7: =Y6*(1-Inputs!$C$13) -> 215006.66
B8: Other Income / Grants ($) | C8: 0 | D8: 0 | E8: 0 | F8: 0 | G8: 0 | H8: 0 | I8: 0 | J8: 0 | K8: 0 | L8: 0 | M8: 0 | N8: 0 | O8: 0 | P8: 0 | Q8: 0 | R8: 0 | S8: 0 | T8: 0 | U8: 0 | V8: 0 | W8: 0 | X8: 0 | Y8: 0 | Z8: 0
B9: TOTAL CASH INFLOWS ($) | C9: =C7+C8 -> 0 | D9: =D7+D8 -> 73500 | E9: =E7+E8 -> 77175 | F9: =F7+F8 -> 81033.75 | G9: =G7+G8 -> 85085.438 | H9: =H7+H8 -> 89339.709 | I9: =I7+I8 -> 93806.695 | J9: =J7+J8 -> 98497.03 | ... Z9: =Z7+Z8 -> 215006.66
B11: CASH OUTFLOWS
B12: Payroll & Burden ($) | C12: =Headcount!J22 -> 59416.667 | D12: =Headcount!K22 -> 68041.667 | E12: =Headcount!L22 -> 82416.667 | F12: =Headcount!M22 -> 87208.333 | G12: =Headcount!N22 -> 87208.333 | H12: =Headcount!O22 -> 95833.333 | I12: =Headcount!P22 -> 104458.33 | J12: =Headcount!Q22 -> 104458.33 | ... Z12: =Headcount!AG22 -> 112815
B13: Opex Payments ($) | C13: 0 | D13: =Opex!F23 -> 34300 | E13: =Opex!G23 -> 35018 | F13: =Opex!H23 -> 35762.68 | G13: =Opex!I23 -> 36535.165 | H13: =Opex!J23 -> 37336.63 | I13: =Opex!K23 -> 38168.305 | J13: =Opex!L23 -> 39031.473 | K13: =Opex!M23 -> 39927.479 | ... Z13: =Opex!AB23 -> 58435.933
B14: Loan Repayments ($) | C14: 0 | D14: 0 | E14: 0 | F14: 0 | G14: 0 | H14: 0 | I14: 0 | J14: 0 | K14: 0 | L14: 0 | M14: 0 | N14: 0 | O14: 0 | P14: 0 | Q14: 0 | R14: 0 | S14: 0 | T14: 0 | U14: 0 | V14: 0 | W14: 0 | X14: 0 | Y14: 0 | Z14: 0
B15: TOTAL CASH OUTFLOWS ($) | C15: =C12+C13+C14 -> 59416.667 | D15: =D12+D13+D14 -> 102341.67 | E15: =E12+E13+E14 -> 117434.67 | F15: =F12+F13+F14 -> 122971.01 | G15: =G12+G13+G14 -> 123743.5 | H15: =H12+H13+H14 -> 133169.96 | I15: =I12+I13+I14 -> 142626.64 | J15: =J12+J13+J14 -> 143489.81 | ... Z15: =Z12+Z13+Z14 -> 171250.93
B17: FINANCING
B18: Net Financing Inflows ($) | C18: =Financing!I10 -> 925000 | D18: =Financing!J10 -> 0 | E18: =Financing!K10 -> 138000 | F18: =Financing!L10 -> 0 | G18: =Financing!M10 -> 0 | H18: =Financing!N10 -> 235000 | I18: =Financing!O10 -> 0 | J18: =Financing!P10 -> 0 | ... Z18: =Financing!AF10 -> 0
B20: CASH POSITION
B21: Net Cash Flow ($) [Inflows − Outflows + Financing] | C21: =C9-C15+C18 -> 865583.33 | D21: =D9-D15+D18 -> -28841.667 | E21: =E9-E15+E18 -> 97740.333 | F21: =F9-F15+F18 -> -41937.263 | G21: =G9-G15+G18 -> -38658.061 | H21: =H9-H15+H18 -> 191169.75 | I21: =I9-I15+I18 -> -48819.943 | J21: =J9-J15+J18 -> -44992.777 | ... Z21: =Z9-Z15+Z18 -> 43755.73
B22: Beginning Cash Balance ($) | C22: =Inputs!$C$6 -> 500000 | D22: =C23 -> 1365583.3 | E22: =D23 -> 1336741.7 | F22: =E23 -> 1434482 | G22: =F23 -> 1392544.7 | H22: =G23 -> 1353886.7 | I22: =H23 -> 1545056.4 | J22: =I23 -> 1496236.5 | K22: =J23 -> 1451243.7 | ... Z22: =Y23 -> 4058980.9
B23: ENDING CASH BALANCE ($) | C23: =C22+C21 -> 1365583.3 | D23: =D22+D21 -> 1336741.7 | E23: =E22+E21 -> 1434482 | F23: =F22+F21 -> 1392544.7 | G23: =G22+G21 -> 1353886.7 | H23: =H22+H21 -> 1545056.4 | I23: =I22+I21 -> 1496236.5 | J23: =J22+J21 -> 1451243.7 | ... Z23: =Z22+Z21 -> 4102736.6
B24: Cash Buffer Check | C24: =IF(C23<Inputs!$C$23,"⚠ BELOW BUFFER","OK") -> OK | D24: =IF(D23<Inputs!$C$23,"⚠ BELOW BUFFER","OK") -> OK | E24: =IF(E23<Inputs!$C$23,"⚠ BELOW BUFFER","OK") -> OK | F24: =IF(F23<Inputs!$C$23,"⚠ BELOW BUFFER","OK") -> OK | G24: =IF(G23<Inputs!$C$23,"⚠ BELOW BUFFER","OK") -> OK | H24: =IF(H23<Inputs!$C$23,"⚠ BELOW BUFFER","OK") -> OK | I24: =IF(I23<Inputs!$C$23,"⚠ BELOW BUFFER","OK") -> OK | J24: =IF(J23<Inputs!$C$23,"⚠ BELOW BUFFER","OK") -> OK | ... Z24: =IF(Z23<Inputs!$C$23,"⚠ BELOW BUFFER","OK") -> OK
B26: Months of Runway | C26: =IF(C27>=0,IFERROR(C23/C27,0),0) -> 22.98317 | D26: =IF(D27>=0,IFERROR(D23/D27,0),0) -> 46.347587 | E26: =IF(E27>=0,IFERROR(E23/E27,0),0) -> 35.630747 | F26: =IF(F27>=0,IFERROR(F23/F27,0),0) -> 33.205427 | G26: =IF(G27>=0,IFERROR(G23/G27,0),0) -> 35.022105 | H26: =IF(H27>=0,IFERROR(H23/H27,0),0) -> 35.250912 | I26: =IF(I27>=0,IFERROR(I23/I27,0),0) -> 30.648059 | J26: =IF(J27>=0,IFERROR(J23/J27,0),0) -> 32.255037 | ... Z26: =IF(Z27>=0,IFERROR(Z23/Z27,0),0) -> 0
B27: Monthly Net Burn Rate ($) | C27: =C15-SUM(C7:C8) -> 59416.667 | D27: =D15-SUM(D7:D8) -> 28841.667 | E27: =E15-SUM(E7:E8) -> 40259.667 | F27: =F15-SUM(F7:F8) -> 41937.263 | G27: =G15-SUM(G7:G8) -> 38658.061 | H27: =H15-SUM(H7:H8) -> 43830.254 | I27: =I15-SUM(I7:I8) -> 48819.943 | J27: =J15-SUM(J7:J8) -> 44992.777 | ... Z27: =Z15-SUM(Z7:Z8) -> -43755.73
B28: Burn Multiple | C28: =IF(C27>=0,IFERROR(ABS(C27)/MAX(C6-B6,1),"-"),0) -> - | D28: =IF(D27>=0,IFERROR(ABS(D27)/MAX(D6-C6,1),"-"),0) -> 7.6911111 | E28: =IF(E27>=0,IFERROR(ABS(E27)/MAX(E6-D6,1),"-"),0) -> 10.224677 | F28: =IF(F27>=0,IFERROR(ABS(F27)/MAX(F6-E6,1),"-"),0) -> 10.143556 | G28: =IF(G27>=0,IFERROR(ABS(G27)/MAX(G6-F6,1),"-"),0) -> 8.905143 | H28: =IF(H27>=0,IFERROR(ABS(H27)/MAX(H6-G6,1),"-"),0) -> 9.6158023 | I28: =IF(I27>=0,IFERROR(ABS(I27)/MAX(I6-H6,1),"-"),0) -> 10.200454 | J28: =IF(J27>=0,IFERROR(ABS(J27)/MAX(J6-I6,1),"-"),0) -> 8.9531474 | ... Z28: =IF(Z27>=0,IFERROR(ABS(Z27)/MAX(Z6-Y6,1),"-"),0) -> 0

Sheet Summary
C1: SUMMARY DASHBOARD
C3: Opening Cash | G3: Total Funding | K3: Cash — Month 24 | O3: Avg Monthly Burn
C4: =Inputs!C6 -> 500000 | G4: =SUM(Financing!I10:AF10) -> 4048000 | K4: ='Cash Flow'!Z23 -> 4102736.6 | O4: =AVERAGE('Cash Flow'!C27:Z27) -> 18552.642
C8: CHART DATA
B9: Month | C9: Jan-2026 | D9: Feb-2026 | E9: Mar-2026 | F9: Apr-2026 | G9: May-2026 | H9: Jun-2026 | I9: Jul-2026 | J9: Aug-2026 | K9: Sep-2026 | L9: Oct-2026 | M9: Nov-2026 | N9: Dec-2026 | O9: Jan-2027 | P9: Feb-2027 | Q9: Mar-2027 | R9: Apr-2027 | S9: May-2027 | T9: Jun-2027 | U9: Jul-2027 | V9: Aug-2027 | W9: Sep-2027 | X9: Oct-2027 | Y9: Nov-2027 | Z9: Dec-2027
B10: Ending Cash ($) | C10: ='Cash Flow'!C23 -> 1365583.3 | D10: ='Cash Flow'!D23 -> 1336741.7 | E10: ='Cash Flow'!E23 -> 1434482 | F10: ='Cash Flow'!F23 -> 1392544.7 | G10: ='Cash Flow'!G23 -> 1353886.7 | H10: ='Cash Flow'!H23 -> 1545056.4 | I10: ='Cash Flow'!I23 -> 1496236.5 | J10: ='Cash Flow'!J23 -> 1451243.7 | ... Z10: ='Cash Flow'!Z23 -> 4102736.6
B11: Net Burn ($) | C11: ='Cash Flow'!C27 -> 59416.667 | D11: ='Cash Flow'!D27 -> 28841.667 | E11: ='Cash Flow'!E27 -> 40259.667 | F11: ='Cash Flow'!F27 -> 41937.263 | G11: ='Cash Flow'!G27 -> 38658.061 | H11: ='Cash Flow'!H27 -> 43830.254 | I11: ='Cash Flow'!I27 -> 48819.943 | J11: ='Cash Flow'!J27 -> 44992.777 | ... Z11: ='Cash Flow'!Z27 -> -43755.73
B12: Total Inflows ($) | C12: ='Cash Flow'!C9 -> 0 | D12: ='Cash Flow'!D9 -> 73500 | E12: ='Cash Flow'!E9 -> 77175 | F12: ='Cash Flow'!F9 -> 81033.75 | G12: ='Cash Flow'!G9 -> 85085.438 | H12: ='Cash Flow'!H9 -> 89339.709 | I12: ='Cash Flow'!I9 -> 93806.695 | J12: ='Cash Flow'!J9 -> 98497.03 | ... Z12: ='Cash Flow'!Z9 -> 215006.66
B13: Total Outflows ($) | C13: ='Cash Flow'!C15 -> 59416.667 | D13: ='Cash Flow'!D15 -> 102341.67 | E13: ='Cash Flow'!E15 -> 117434.67 | F13: ='Cash Flow'!F15 -> 122971.01 | G13: ='Cash Flow'!G15 -> 123743.5 | H13: ='Cash Flow'!H15 -> 133169.96 | I13: ='Cash Flow'!I15 -> 142626.64 | J13: ='Cash Flow'!J15 -> 143489.81 | ... Z13: ='Cash Flow'!Z15 -> 171250.93
B14: Runway (months) | C14: ='Cash Flow'!C26 -> 22.98317 | D14: ='Cash Flow'!D26 -> 46.347587 | E14: ='Cash Flow'!E26 -> 35.630747 | F14: ='Cash Flow'!F26 -> 33.205427 | G14: ='Cash Flow'!G26 -> 35.022105 | H14: ='Cash Flow'!H26 -> 35.250912 | I14: ='Cash Flow'!I26 -> 30.648059 | J14: ='Cash Flow'!J26 -> 32.255037 | ... Z14: ='Cash Flow'!Z26 -> 0
