Workbook

Sheet Instructions
B2: Step-by-Step Instructions
B4: Steps | C4: Details
B5: 1 | C5: Go to the “Inputs” sheet
B6: 2 | C6: Fill in your data for each year (left to right)
B7: 3 | C7: Enter data only into the light blue colored cells (do not edit formulas)
B8: 4 | C8: Leave unused years blank
B9: 5 | C9: View results in the “Dashboard” sheet
B12: What Each Input Means
B14: Metric | E14: Description
B15: Marketing Spend | E15: Total amount spent on marketing activities (ads, campaigns, tools) for the year
B16: Sales Cost | E16: Expenses related to sales team (salaries, commissions, CRM tools, etc.)
B17: New Customers | E17: Total number of new customers acquired during the year
B18: ARPU (Average Revenue Per User) | E18: Average monthly revenue generated per customer
B19: Gross Margin (%) | E19: Percentage of revenue retained after direct costs (e.g., cost of goods/services)
B20: Customer Lifespan (Months) | E20: Average duration a customer stays with your business
B21: Churn Rate (%) | E21: Percentage of customers lost each month
B24: Important Guidelines
B26: Guideline | E26: Description
B27: Enter data left to right | E27: Fill data from oldest year to latest (e.g., 2022 → 2025)
B28: Fill only input cells | E28: Enter values only in highlighted cells; do not edit formulas
B29: Leave unused years blank | E29: Keep empty cells blank (do not enter anything into it)
B30: Use consistent units | E30: Ensure all values use the same currency and format

Sheet Dashboard
C3: Key Unit Economics
C5: CAC | F5: CLTV | I5: CLTV:CAC | L5: Payback | O5: Profit
C6: {=LOOKUP(2,1/(Calculations!C3:G3<>""),Calculations!C3:G3)} -> 7666.6667 | F6: {=LOOKUP(2,1/(Calculations!C4:G4<>""),Calculations!C4:G4)} -> 6000 | I6: {=LOOKUP(2,1/(Calculations!C5:G5<>""),Calculations!C5:G5)} -> 0.7826087 | L6: {=LOOKUP(2,1/(Calculations!C6:G6<>""),Calculations!C6:G6)} -> 6.3888889 | O6: {=LOOKUP(2,1/(Calculations!C7:G7<>""),Calculations!C7:G7)} -> -1666.6667
H11: Overall Business Health
H12: =IF(I6<1,"Not Viable",IF(I6<3,"Needs Improvement","Healthy")) -> Not Viable
H14: =IF(H12="Not Viable","Losing money per customer",IF(H12="Needs Improvement","Unit economics need optimization","Strong unit economics, ready to scale")) -> Losing money per customer
K17: Benchmark ratio | M17: 3
H36: Key Insights
H38: =IF(F6>C6,"CLTV exceeds CAC → profitable","CAC too high vs CLTV") -> CAC too high vs CLTV | AE38: {=INDEX(Calculations!C5:G5,MATCH(2,1/(Calculations!C5:G5<>""),1)-1)} -> 0.71875
H39: =IF(I6>AE38,"Efficiency improving","Efficiency declining") -> Efficiency improving | AE39: {=INDEX(Calculations!C6:G6,MATCH(2,1/(Calculations!C6:G6<>""),1)-1)} -> 7.9503106
H40: =IF(L6<AE39,"Faster cost recovery","Slower payback period") -> Faster cost recovery

Sheet Inputs
B2: Metric | C2: Year 1 | D2: Year 2 | E2: Year 3 | F2: Year 4 | G2: Year 5
B3: Marketing Spend | C3: 1000000 | D3: 1250000 | E3: 1500000 | F3: 1750000 | G3: 2000000
B4: Sales Cost | C4: 100000 | D4: 150000 | E4: 200000 | F4: 250000 | G4: 300000
B5: New Customers | C5: 100 | D5: 150 | E5: 200 | F5: 250 | G5: 300
B6: ARPU (Monthly) | C6: 1000 | D6: 1250 | E6: 1500 | F6: 1750 | G6: 2000
B7: Gross Margin (%) | C7: 0.5 | D7: 0.525 | E7: 0.55 | F7: 0.575 | G7: 0.6
B8: Lifespan (months) | C8: 1 | D8: 1.25 | E8: 1.5 | F8: 1.75 | G8: 2
B9: Churn Rate (%) | C9: 0.1 | D9: 0.125 | E9: 0.15 | F9: 0.175 | G9: 0.2

Sheet Calculations
B2: Metric | C2: Year 1 | D2: Year 2 | E2: Year 3 | F2: Year 4 | G2: Year 5
B3: Customer Acquisition Cost (CAC) | C3: =SUM(Inputs!C3:C4)/Inputs!C5 -> 11000 | D3: =SUM(Inputs!D3:D4)/Inputs!D5 -> 9333.3333 | E3: =SUM(Inputs!E3:E4)/Inputs!E5 -> 8500 | F3: =SUM(Inputs!F3:F4)/Inputs!F5 -> 8000 | G3: =SUM(Inputs!G3:G4)/Inputs!G5 -> 7666.6667
B4: Customer Lifetime Value (CLTV) | C4: =(Inputs!C6*Inputs!C7)/Inputs!C9 -> 5000 | D4: =(Inputs!D6*Inputs!D7)/Inputs!D9 -> 5250 | E4: =(Inputs!E6*Inputs!E7)/Inputs!E9 -> 5500 | F4: =(Inputs!F6*Inputs!F7)/Inputs!F9 -> 5750 | G4: =(Inputs!G6*Inputs!G7)/Inputs!G9 -> 6000
B5: CLTV:CAC Ratio | C5: =C4/C3 -> 0.45454545 | D5: =D4/D3 -> 0.5625 | E5: =E4/E3 -> 0.64705882 | F5: =F4/F3 -> 0.71875 | G5: =G4/G3 -> 0.7826087
B6: Payback Period (in months) | C6: =C3/(Inputs!C6*Inputs!C7) -> 22 | D6: =D3/(Inputs!D6*Inputs!D7) -> 14.222222 | E6: =E3/(Inputs!E6*Inputs!E7) -> 10.30303 | F6: =F3/(Inputs!F6*Inputs!F7) -> 7.9503106 | G6: =G3/(Inputs!G6*Inputs!G7) -> 6.3888889
B7: Profit per Customer | C7: =C4-C3 -> -6000 | D7: =D4-D3 -> -4083.3333 | E7: =E4-E3 -> -3000 | F7: =F4-F3 -> -2250 | G7: =G4-G3 -> -1666.6667
