Workbook

Sheet Instructions
C2: → Manual Input Required
B4: STARTUP MIS TEMPLATE FOR MANUFACTURING BUSINESS — INSTRUCTIONS FOR USE
B6: GENERAL INSTRUCTIONS
B8: • Cells highlighted in Light Blue are designated for manual data entry unless otherwise specified.
B9: • While entering numerical values, do not use commas (,) or negative signs (-) unless specifically instructed.
B10: • All other cells contain formulas and should not be modified.
B11: • It is recommended to update all relevant input sheets before reviewing the Dashboard and KPI outputs.
B13: DASHBOARD SHEET
B15: The only manual inputs required in this sheet are the following fields under the Basic Details section:
B17: • Company Name
B18: • Industry
B19: • Reporting Month
B20: • Prepared By
... B117: Please ensure all relevant data has been updated before reviewing the outputs.

Sheet Dashboard
D2: Company Name | E2: ABC Pvt Ltd
D3: Industry | E3: Manufacturing
D4: Reporting Month | E4: 46082
D5: Prepared By | E5: XXX
D8: MONTHLY MIS DASHBOARD
D10: Revenue | F10: Gross Profit | H10: EBITDA
D11: ='P&L'!O3 -> 6450000 | F11: ='P&L'!O5 -> 5456720.2 | H11: ='P&L'!O9 -> 4856613.6 | J11: Gross Margin % | K11: ='KPI & Ratio Analysis'!C7 -> 0.84600313
J12: EBITDA Margin % | K12: ='KPI & Ratio Analysis'!C8 -> 0.75296335
J13: Net Margin % | K13: ='KPI & Ratio Analysis'!C9 -> 0.6984228
J14: Current Ratio | K14: ='KPI & Ratio Analysis'!C16 -> 2.0208333
D15: Net Profit | F15: Cash Balance | H15: Production Quantity | J15: Runway | K15: ='KPI & Ratio Analysis'!C13 -> 152
D16: ='P&L'!O17 -> 4504827 | F16: =CFS!O21 -> 760000 | H16: ='Manufacturing Metrics'!C3 -> 100000

Sheet Revenue MIS
B2: Previous Year Revenue | C2: 5000000
B5: Month | C5: Product Sales | D5: Contract Manufacturing Revenue | E5: Export Sales | F5: Service & Maintenance Revenue | G5: Other Revenue | H5: Total Revenue | I5: Growth %
B6: Apr | C6: 100000 | D6: 90000 | E6: 80000 | F6: 70000 | G6: 60000 | H6: =SUM(C6:G6) -> 400000
B7: May | C7: 105000 | D7: 95000 | E7: 85000 | F7: 75000 | G7: 65000 | H7: =SUM(C7:G7) -> 425000 | I7: =H7/H6-1 -> 0.0625
B8: Jun | C8: 110000 | D8: 100000 | E8: 90000 | F8: 80000 | G8: 70000 | H8: =SUM(C8:G8) -> 450000 | I8: =H8/H7-1 -> 0.058823529
B9: Jul | C9: 115000 | D9: 105000 | E9: 95000 | F9: 85000 | G9: 75000 | H9: =SUM(C9:G9) -> 475000 | I9: =H9/H8-1 -> 0.055555556
B10: Aug | C10: 120000 | D10: 110000 | E10: 100000 | F10: 90000 | G10: 80000 | H10: =SUM(C10:G10) -> 500000 | I10: =H10/H9-1 -> 0.052631579
B11: Sep | C11: 125000 | D11: 115000 | E11: 105000 | F11: 95000 | G11: 85000 | H11: =SUM(C11:G11) -> 525000 | I11: =H11/H10-1 -> 0.05
B12: Oct | C12: 130000 | D12: 120000 | E12: 110000 | F12: 100000 | G12: 90000 | H12: =SUM(C12:G12) -> 550000 | I12: =H12/H11-1 -> 0.047619048
B13: Nov | C13: 135000 | D13: 125000 | E13: 115000 | F13: 105000 | G13: 95000 | H13: =SUM(C13:G13) -> 575000 | I13: =H13/H12-1 -> 0.045454545
B14: Dec | C14: 140000 | D14: 130000 | E14: 120000 | F14: 110000 | G14: 100000 | H14: =SUM(C14:G14) -> 600000 | I14: =H14/H13-1 -> 0.043478261
B15: Jan | C15: 145000 | D15: 135000 | E15: 125000 | F15: 115000 | G15: 105000 | H15: =SUM(C15:G15) -> 625000 | I15: =H15/H14-1 -> 0.041666667
B16: Feb | C16: 150000 | D16: 140000 | E16: 130000 | F16: 120000 | G16: 110000 | H16: =SUM(C16:G16) -> 650000 | I16: =H16/H15-1 -> 0.04
B17: Mar | C17: 155000 | D17: 145000 | E17: 135000 | F17: 125000 | G17: 115000 | H17: =SUM(C17:G17) -> 675000 | I17: =H17/H16-1 -> 0.038461538
B18: Total | C18: =SUM(C6:C17) -> 1530000 | D18: =SUM(D6:D17) -> 1410000 | E18: =SUM(E6:E17) -> 1290000 | F18: =SUM(F6:F17) -> 1170000 | G18: =SUM(G6:G17) -> 1050000 | H18: =SUM(H6:H17) -> 6450000
B21: Month | C21: Target Revenue | D21: Actual Revenue | E21: Variance | F21: Variance %
B22: Apr | C22: 320000 | D22: =H6 -> 400000 | E22: =D22-C22 -> 80000 | F22: =E22/C22 -> 0.25
B23: May | C23: 340000 | D23: =H7 -> 425000 | E23: =D23-C23 -> 85000 | F23: =E23/C23 -> 0.25
B24: Jun | C24: 405000 | D24: =H8 -> 450000 | E24: =D24-C24 -> 45000 | F24: =E24/C24 -> 0.11111111
B25: Jul | C25: 522500 | D25: =H9 -> 475000 | E25: =D25-C25 -> -47500 | F25: =E25/C25 -> -0.090909091
B26: Aug | C26: 550000 | D26: =H10 -> 500000 | E26: =D26-C26 -> -50000 | F26: =E26/C26 -> -0.090909091
B27: Sep | C27: 630000 | D27: =H11 -> 525000 | E27: =D27-C27 -> -105000 | F27: =E27/C27 -> -0.16666667
B28: Oct | C28: 550000 | D28: =H12 -> 550000 | E28: =D28-C28 -> 0 | F28: =E28/C28 -> 0
B29: Nov | C29: 431250 | D29: =H13 -> 575000 | E29: =D29-C29 -> 143750 | F29: =E29/C29 -> 0.33333333
B30: Dec | C30: 420000 | D30: =H14 -> 600000 | E30: =D30-C30 -> 180000 | F30: =E30/C30 -> 0.42857143
B31: Jan | C31: 312500 | D31: =H15 -> 625000 | E31: =D31-C31 -> 312500 | F31: =E31/C31 -> 1
B32: Feb | C32: 812500 | D32: =H16 -> 650000 | E32: =D32-C32 -> -162500 | F32: =E32/C32 -> -0.2
B33: Mar | C33: 877500 | D33: =H17 -> 675000 | E33: =D33-C33 -> -202500 | F33: =E33/C33 -> -0.23076923
B34: Total | C34: =SUM(C22:C33) -> 6171250 | D34: =SUM(D22:D33) -> 6450000 | E34: =SUM(E22:E33) -> 278750

Sheet Expense MIS
B2: Expense Head | C2: Apr | D2: May | E2: Jun | F2: Jul | G2: Aug | H2: Sep | I2: Oct | J2: Nov | K2: Dec | L2: Jan | M2: Feb | N2: Mar | O2: Total
B3: Direct Costs (COGS):
B4: Raw Material Cost | C4: 25000 | D4: 25625 | E4: 26265.625 | F4: 26922.266 | G4: 27595.322 | H4: 28285.205 | I4: 28992.335 | J4: 29717.144 | K4: 30460.072 | L4: 31221.574 | M4: 32002.114 | N4: 32802.166 | O4: =SUM(C4:N4) -> 344888.82
B5: Direct Labour Cost | C5: 40000 | D5: 41000 | E5: 42025 | F5: 43075.625 | G5: 44152.516 | H5: 45256.329 | I5: 46387.737 | J5: 47547.43 | K5: 48736.116 | L5: 49954.519 | M5: 51203.382 | N5: 52483.466 | O5: =SUM(C5:N5) -> 551822.12
B6: Power & Fuel | C6: 2000 | D6: 2050 | E6: 2101.25 | F6: 2153.7812 | G6: 2207.6258 | H6: 2262.8164 | I6: 2319.3868 | J6: 2377.3715 | K6: 2436.8058 | L6: 2497.7259 | M6: 2560.1691 | N6: 2624.1733 | O6: =SUM(C6:N6) -> 27591.106
B7: Factory Overheads | C7: 5000 | D7: 5125 | E7: 5253.125 | F7: 5384.4531 | G7: 5519.0645 | H7: 5657.0411 | I7: 5798.4671 | J7: 5943.4288 | K7: 6092.0145 | L7: 6244.3148 | M7: 6400.4227 | N7: 6560.4333 | O7: =SUM(C7:N7) -> 68977.765
B9: Operating Expenses:
B10: Repairs & Maintenance | C10: 1000 | D10: 1025 | E10: 1050.625 | F10: 1076.8906 | G10: 1103.8129 | H10: 1131.4082 | I10: 1159.6934 | J10: 1188.6858 | K10: 1218.4029 | L10: 1248.863 | M10: 1280.0845 | N10: 1312.0867 | O10: =SUM(C10:N10) -> 13795.553
B11: Salaries & Administrative Expenses | C11: 5000 | D11: 5125 | E11: 5253.125 | F11: 5384.4531 | G11: 5519.0645 | H11: 5657.0411 | I11: 5798.4671 | J11: 5943.4288 | K11: 6092.0145 | L11: 6244.3148 | M11: 6400.4227 | N11: 6560.4333 | O11: =SUM(C11:N11) -> 68977.765
B12: Selling & Marketing Expenses | C12: 3000 | D12: 3075 | E12: 3151.875 | F12: 3230.6719 | G12: 3311.4387 | H12: 3394.2246 | I12: 3479.0803 | J12: 3566.0573 | K12: 3655.2087 | L12: 3746.5889 | M12: 3840.2536 | N12: 3936.26 | O12: =SUM(C12:N12) -> 41386.659
B13: Logistics & Transportation | C13: 5000 | D13: 5125 | E13: 5253.125 | F13: 5384.4531 | G13: 5519.0645 | H13: 5657.0411 | I13: 5798.4671 | J13: 5943.4288 | K13: 6092.0145 | L13: 6244.3148 | M13: 6400.4227 | N13: 6560.4333 | O13: =SUM(C13:N13) -> 68977.765
B14: Professional Fees | C14: 2000 | D14: 2050 | E14: 2101.25 | F14: 2153.7812 | G14: 2207.6258 | H14: 2262.8164 | I14: 2319.3868 | J14: 2377.3715 | K14: 2436.8058 | L14: 2497.7259 | M14: 2560.1691 | N14: 2624.1733 | O14: =SUM(C14:N14) -> 27591.106
B15: Miscellaneous | C15: 2000 | D15: 2050 | E15: 2101.25 | F15: 2153.7812 | G15: 2207.6258 | H15: 2262.8164 | I15: 2319.3868 | J15: 2377.3715 | K15: 2436.8058 | L15: 2497.7259 | M15: 2560.1691 | N15: 2624.1733 | O15: =SUM(C15:N15) -> 27591.106
B16: Interest Expense | C16: 5000 | D16: 5125 | E16: 5253.125 | F16: 5384.4531 | G16: 5519.0645 | H16: 5657.0411 | I16: 5798.4671 | J16: 5943.4288 | K16: 6092.0145 | L16: 6244.3148 | M16: 6400.4227 | N16: 6560.4333 | O16: =SUM(C16:N16) -> 68977.765
B17: Bank Charges | C17: 500 | D17: 512.5 | E17: 525.3125 | F17: 538.44531 | G17: 551.90645 | H17: 565.70411 | I17: 579.84671 | J17: 594.34288 | K17: 609.20145 | L17: 624.43148 | M17: 640.04227 | N17: 656.04333 | O17: =SUM(C17:N17) -> 6897.7765
B18: Depreciation & Amortization | C18: 10000 | D18: 10250 | E18: 10506.25 | F18: 10768.906 | G18: 11038.129 | H18: 11314.082 | I18: 11596.934 | J18: 11886.858 | K18: 12184.029 | L18: 12488.63 | M18: 12800.845 | N18: 13120.867 | O18: =SUM(C18:N18) -> 137955.53
B19: Provision for Tax | C19: 10000 | D19: 10250 | E19: 10506.25 | F19: 10768.906 | G19: 11038.129 | H19: 11314.082 | I19: 11596.934 | J19: 11886.858 | K19: 12184.029 | L19: 12488.63 | M19: 12800.845 | N19: 13120.867 | O19: =SUM(C19:N19) -> 137955.53
B20: Total Expenses | C20: =SUM(C4:C19) -> 115500 | D20: =SUM(D4:D19) -> 118387.5 | E20: =SUM(E4:E19) -> 121347.19 | F20: =SUM(F4:F19) -> 124380.87 | G20: =SUM(G4:G19) -> 127490.39 | H20: =SUM(H4:H19) -> 130677.65 | I20: =SUM(I4:I19) -> 133944.59 | J20: =SUM(J4:J19) -> 137293.2 | ... N20: =SUM(N4:N19) -> 151546.01 | O20: =SUM(C20:N20) -> 1593386.4
B23: Expense Head | C23: Budget | D23: Actual | E23: Variance | F23: Variance %
B24: Direct Costs (COGS):
B25: Raw Material Cost | C25: 310399.94 | D25: =O4 -> 344888.82 | E25: =D25-C25 -> 34488.882 | F25: =E25/C25 -> 0.11111111
B26: Direct Labour Cost | C26: 441457.7 | D26: =O5 -> 551822.12 | E26: =D26-C26 -> 110364.42 | F26: =E26/C26 -> 0.25
B27: Power & Fuel | C27: 19313.774 | D27: =O6 -> 27591.106 | E27: =D27-C27 -> 8277.3318 | F27: =E27/C27 -> 0.42857143
B28: Factory Overheads | C28: 75875.541 | D28: =O7 -> 68977.765 | E28: =D28-C28 -> -6897.7765 | F28: =E28/C28 -> -0.090909091
B30: Operating Expenses:
B31: Repairs & Maintenance | C31: 9656.8871 | D31: =O10 -> 13795.553 | E31: =D31-C31 -> 4138.6659 | F31: =E31/C31 -> 0.42857143
B32: Salaries & Administrative Expenses | C32: 75875.541 | D32: =O11 -> 68977.765 | E32: =D32-C32 -> -6897.7765 | F32: =E32/C32 -> -0.090909091
B33: Selling & Marketing Expenses | C33: 49663.991 | D33: =O12 -> 41386.659 | E33: =D33-C33 -> -8277.3318 | F33: =E33/C33 -> -0.16666667
B34: Logistics & Transportation | C34: 89671.094 | D34: =O13 -> 68977.765 | E34: =D34-C34 -> -20693.329 | F34: =E34/C34 -> -0.23076923
B35: Professional Fees | C35: 24831.995 | D35: =O14 -> 27591.106 | E35: =D35-C35 -> 2759.1106 | F35: =E35/C35 -> 0.11111111
B36: Miscellaneous | C36: 24831.995 | D36: =O15 -> 27591.106 | E36: =D36-C36 -> 2759.1106 | F36: =E36/C36 -> 0.11111111
B37: Interest Expense | C37: 62079.988 | D37: =O16 -> 68977.765 | E37: =D37-C37 -> 6897.7765 | F37: =E37/C37 -> 0.11111111
B38: Bank Charges | C38: 6207.9988 | D38: =O17 -> 6897.7765 | E38: =D38-C38 -> 689.77765 | F38: =E38/C38 -> 0.11111111
B39: Depreciation & Amortization | C39: 124159.98 | D39: =O18 -> 137955.53 | E39: =D39-C39 -> 13795.553 | F39: =E39/C39 -> 0.11111111
B40: Provision for Tax | C40: 124159.98 | D40: =O19 -> 137955.53 | E40: =D40-C40 -> 13795.553 | F40: =E40/C40 -> 0.11111111
B41: Total | C41: =SUM(C25:C40) -> 1438186.4 | D41: =SUM(D25:D40) -> 1593386.4 | E41: =SUM(E25:E40) -> 155199.97

Sheet Manufacturing Metrics
B2: Particulars | C2: Value
B3: Production Quantity | C3: 100000
B4: Units Sold | C4: 92000
B5: Production Capacity | C5: 120000
B6: Defective Units | C6: 3000
B9: Particulars | C9: Value
B10: Capacity Utilization % | C10: =C3/C5 -> 0.83333333
B11: Sales Realization per Unit | C11: ='Revenue MIS'!H18/'Manufacturing Metrics'!C4 -> 70.108696
B12: Defect Rate % | C12: =C6/C5 -> 0.025
B13: Production Efficiency % | C13: =C4/C3 -> 0.92

Sheet P&L
B2: Particulars | C2: Apr | D2: May | E2: Jun | F2: Jul | G2: Aug | H2: Sep | I2: Oct | J2: Nov | K2: Dec | L2: Jan | M2: Feb | N2: Mar | O2: Total
B3: Total Revenue | C3: {=TRANSPOSE('Revenue MIS'!H6:H17)} -> 400000 | D3: 425000 | E3: 450000 | F3: 475000 | G3: 500000 | H3: 525000 | I3: 550000 | J3: 575000 | K3: 600000 | L3: 625000 | M3: 650000 | N3: 675000 | O3: =SUM(C3:N3) -> 6450000
B4: Total Direct Costs (COGS) | C4: =-SUM('Expense MIS'!C4:C7) -> -72000 | D4: =-SUM('Expense MIS'!D4:D7) -> -73800 | E4: =-SUM('Expense MIS'!E4:E7) -> -75645 | F4: =-SUM('Expense MIS'!F4:F7) -> -77536.125 | G4: =-SUM('Expense MIS'!G4:G7) -> -79474.528 | H4: =-SUM('Expense MIS'!H4:H7) -> -81461.391 | I4: =-SUM('Expense MIS'!I4:I7) -> -83497.926 | J4: =-SUM('Expense MIS'!J4:J7) -> -85585.374 | ... N4: =-SUM('Expense MIS'!N4:N7) -> -94470.239 | O4: =SUM(C4:N4) -> -993279.81
B5: Gross Profit | C5: =SUM(C3:C4) -> 328000 | D5: =SUM(D3:D4) -> 351200 | E5: =SUM(E3:E4) -> 374355 | F5: =SUM(F3:F4) -> 397463.88 | G5: =SUM(G3:G4) -> 420525.47 | H5: =SUM(H3:H4) -> 443538.61 | I5: =SUM(I3:I4) -> 466502.07 | J5: =SUM(J3:J4) -> 489414.63 | ... N5: =SUM(N3:N4) -> 580529.76 | O5: =SUM(C5:N5) -> 5456720.2
B6: Gross Margin % | C6: =C5/C3 -> 0.82 | D6: =D5/D3 -> 0.82635294 | E6: =E5/E3 -> 0.8319 | F6: =F5/F3 -> 0.83676605 | G6: =G5/G3 -> 0.84105094 | H6: =H5/H3 -> 0.84483545 | I6: =I5/I3 -> 0.84818559 | J6: =J5/J3 -> 0.85115587 | ... O6: =O5/O3 -> 0.84600313
B8: Total Operating Expenses | C8: =-SUM('Expense MIS'!C10:C19) -> -43500 | D8: =-SUM('Expense MIS'!D10:D19) -> -44587.5 | E8: =-SUM('Expense MIS'!E10:E19) -> -45702.187 | F8: =-SUM('Expense MIS'!F10:F19) -> -46844.742 | G8: =-SUM('Expense MIS'!G10:G19) -> -48015.861 | H8: =-SUM('Expense MIS'!H10:H19) -> -49216.257 | I8: =-SUM('Expense MIS'!I10:I19) -> -50446.664 | J8: =-SUM('Expense MIS'!J10:J19) -> -51707.83 | ... N8: =-SUM('Expense MIS'!N10:N19) -> -57075.77 | O8: =SUM(C8:N8) -> -600106.55
B9: EBITDA | C9: =C5+C8 -> 284500 | D9: =D5+D8 -> 306612.5 | E9: =E5+E8 -> 328652.81 | F9: =F5+F8 -> 350619.13 | G9: =G5+G8 -> 372509.61 | H9: =H5+H8 -> 394322.35 | I9: =I5+I8 -> 416055.41 | J9: =J5+J8 -> 437706.8 | ... N9: =N5+N8 -> 523453.99 | O9: =SUM(C9:N9) -> 4856613.6
B10: EBITDA Margin % | C10: =C9/C3 -> 0.71125 | D10: =D9/D3 -> 0.72144118 | E10: =E9/E3 -> 0.73033958 | F10: =F9/F3 -> 0.73814554 | G10: =G9/G3 -> 0.74501922 | H10: =H9/H3 -> 0.75109019 | I10: =I9/I3 -> 0.75646438 | J10: =J9/J3 -> 0.76122921 | ... O10: =O9/O3 -> 0.75296335
B12: Interest & Bank Charges | C12: =-SUM('Expense MIS'!C$16:C$17) -> -5500 | D12: =-SUM('Expense MIS'!D$16:D$17) -> -5637.5 | E12: =-SUM('Expense MIS'!E$16:E$17) -> -5778.4375 | F12: =-SUM('Expense MIS'!F$16:F$17) -> -5922.8984 | G12: =-SUM('Expense MIS'!G$16:G$17) -> -6070.9709 | H12: =-SUM('Expense MIS'!H$16:H$17) -> -6222.7452 | I12: =-SUM('Expense MIS'!I$16:I$17) -> -6378.3138 | J12: =-SUM('Expense MIS'!J$16:J$17) -> -6537.7716 | ... N12: =-SUM('Expense MIS'!N$16:N$17) -> -7216.4766 | O12: =SUM(C12:N12) -> -75875.541
B13: Depreciation & Amortization | C13: =-'Expense MIS'!C$18 -> -10000 | D13: =-'Expense MIS'!D$18 -> -10250 | E13: =-'Expense MIS'!E$18 -> -10506.25 | F13: =-'Expense MIS'!F$18 -> -10768.906 | G13: =-'Expense MIS'!G$18 -> -11038.129 | H13: =-'Expense MIS'!H$18 -> -11314.082 | I13: =-'Expense MIS'!I$18 -> -11596.934 | J13: =-'Expense MIS'!J$18 -> -11886.858 | ... N13: =-'Expense MIS'!N$18 -> -13120.867 | O13: =SUM(C13:N13) -> -137955.53
B14: Profit Before Tax (PBT) | C14: =SUM(C9,C12:C13) -> 269000 | D14: =SUM(D9,D12:D13) -> 290725 | E14: =SUM(E9,E12:E13) -> 312368.12 | F14: =SUM(F9,F12:F13) -> 333927.33 | G14: =SUM(G9,G12:G13) -> 355400.51 | H14: =SUM(H9,H12:H13) -> 376785.52 | I14: =SUM(I9,I12:I13) -> 398080.16 | J14: =SUM(J9,J12:J13) -> 419282.17 | ... N14: =SUM(N9,N12:N13) -> 503116.65 | O14: =SUM(C14:N14) -> 4642782.6
B16: Tax Expense | C16: =-'Expense MIS'!C$19 -> -10000 | D16: =-'Expense MIS'!D$19 -> -10250 | E16: =-'Expense MIS'!E$19 -> -10506.25 | F16: =-'Expense MIS'!F$19 -> -10768.906 | G16: =-'Expense MIS'!G$19 -> -11038.129 | H16: =-'Expense MIS'!H$19 -> -11314.082 | I16: =-'Expense MIS'!I$19 -> -11596.934 | J16: =-'Expense MIS'!J$19 -> -11886.858 | ... N16: =-'Expense MIS'!N$19 -> -13120.867 | O16: =SUM(C16:N16) -> -137955.53
B17: Net Profit | C17: =SUM(C14,C16) -> 259000 | D17: =SUM(D14,D16) -> 280475 | E17: =SUM(E14,E16) -> 301861.88 | F17: =SUM(F14,F16) -> 323158.42 | G17: =SUM(G14,G16) -> 344362.38 | H17: =SUM(H14,H16) -> 365471.44 | I17: =SUM(I14,I16) -> 386483.23 | J17: =SUM(J14,J16) -> 407395.31 | ... N17: =SUM(N14,N16) -> 489995.78 | O17: =SUM(C17:N17) -> 4504827
B18: Net Margin % | C18: =C17/C3 -> 0.6475 | D18: =D17/D3 -> 0.65994118 | E18: =E17/E3 -> 0.67080417 | F18: =F17/F3 -> 0.68033352 | G18: =G17/G3 -> 0.68872476 | H18: =H17/H3 -> 0.69613608 | I18: =I17/I3 -> 0.70269678 | J18: =J17/J3 -> 0.70851358 | ... O18: =O17/O3 -> 0.6984228

Sheet CFS
B2: Particulars | C2: Apr | D2: May | E2: Jun | F2: Jul | G2: Aug | H2: Sep | I2: Oct | J2: Nov | K2: Dec | L2: Jan | M2: Feb | N2: Mar | O2: Total
B3: Cash Received from Customers | C3: 200000 | D3: 205000 | E3: 210000 | F3: 215000 | G3: 220000 | H3: 225000 | I3: 230000 | J3: 235000 | K3: 240000 | L3: 245000 | M3: 250000 | N3: 255000 | O3: =SUM(C3:N3) -> 2730000
B4: Payments to Suppliers | C4: -100000 | D4: -105000 | E4: -110000 | F4: -115000 | G4: -120000 | H4: -125000 | I4: -130000 | J4: -135000 | K4: -140000 | L4: -145000 | M4: -150000 | N4: -155000 | O4: =SUM(C4:N4) -> -1530000
B5: Salary Payments | C5: -10000 | D5: -15000 | E5: -20000 | F5: -25000 | G5: -30000 | H5: -35000 | I5: -40000 | J5: -45000 | K5: -50000 | L5: -55000 | M5: -60000 | N5: -65000 | O5: =SUM(C5:N5) -> -450000
B6: Operating Expenses Paid | C6: -30000 | D6: -35000 | E6: -40000 | F6: -45000 | G6: -50000 | H6: -55000 | I6: -60000 | J6: -65000 | K6: -70000 | L6: -75000 | M6: -80000 | N6: -85000 | O6: =SUM(C6:N6) -> -690000
B7: Net Cash from Operations | C7: =SUM(C3:C6) -> 60000 | D7: =SUM(D3:D6) -> 50000 | E7: =SUM(E3:E6) -> 40000 | F7: =SUM(F3:F6) -> 30000 | G7: =SUM(G3:G6) -> 20000 | H7: =SUM(H3:H6) -> 10000 | I7: =SUM(I3:I6) -> 0 | J7: =SUM(J3:J6) -> -10000 | ... N7: =SUM(N3:N6) -> -50000 | O7: =SUM(C7:N7) -> 60000
B9: Purchase of Equipment | C9: -250000 | O9: =SUM(C9:N9) -> -250000
B10: Purchase of Assets | H10: -100000 | O10: =SUM(C10:N10) -> -100000
B11: Net Cash from Investing | C11: =SUM(C9:C10) -> -250000 | D11: =SUM(D9:D10) -> 0 | E11: =SUM(E9:E10) -> 0 | F11: =SUM(F9:F10) -> 0 | G11: =SUM(G9:G10) -> 0 | H11: =SUM(H9:H10) -> -100000 | I11: =SUM(I9:I10) -> 0 | J11: =SUM(J9:J10) -> 0 | ... N11: =SUM(N9:N10) -> 0 | O11: =SUM(C11:N11) -> -350000
B13: Capital Introduced | C13: 1000000 | O13: =SUM(C13:N13) -> 1000000
B14: Loan Received | C14: 500000 | O14: =SUM(C14:N14) -> 500000
B15: Loan Repayment | D15: -100000 | E15: -100000 | F15: -100000 | G15: -100000 | H15: -100000 | O15: =SUM(C15:N15) -> -500000
B16: Interest Paid | D16: -10000 | E16: -10000 | F16: -10000 | G16: -10000 | H16: -10000 | O16: =SUM(C16:N16) -> -50000
B17: Net Cash from Financing | C17: =SUM(C13:C16) -> 1500000 | D17: =SUM(D13:D16) -> -110000 | E17: =SUM(E13:E16) -> -110000 | F17: =SUM(F13:F16) -> -110000 | G17: =SUM(G13:G16) -> -110000 | H17: =SUM(H13:H16) -> -110000 | I17: =SUM(I13:I16) -> 0 | J17: =SUM(J13:J16) -> 0 | ... N17: =SUM(N13:N16) -> 0 | O17: =SUM(C17:N17) -> 950000
B19: Opening Cash & Cash Equivalents | C19: 100000 | D19: =C21 -> 1410000 | E19: =D21 -> 1350000 | F19: =E21 -> 1280000 | G19: =F21 -> 1200000 | H19: =G21 -> 1110000 | I19: =H21 -> 910000 | J19: =I21 -> 910000 | K19: =J21 -> 900000 | ... N19: =M21 -> 810000 | O19: =C19 -> 100000
B20: Change in Cash & Cash Equivalents | C20: =SUM(C7,C11,C17) -> 1310000 | D20: =SUM(D7,D11,D17) -> -60000 | E20: =SUM(E7,E11,E17) -> -70000 | F20: =SUM(F7,F11,F17) -> -80000 | G20: =SUM(G7,G11,G17) -> -90000 | H20: =SUM(H7,H11,H17) -> -200000 | I20: =SUM(I7,I11,I17) -> 0 | J20: =SUM(J7,J11,J17) -> -10000 | ... N20: =SUM(N7,N11,N17) -> -50000 | O20: =SUM(C20:N20) -> 660000
B21: Closing Cash & Cash Equivalents | C21: =SUM(C19:C20) -> 1410000 | D21: =SUM(D19:D20) -> 1350000 | E21: =SUM(E19:E20) -> 1280000 | F21: =SUM(F19:F20) -> 1200000 | G21: =SUM(G19:G20) -> 1110000 | H21: =SUM(H19:H20) -> 910000 | I21: =SUM(I19:I20) -> 910000 | J21: =SUM(J19:J20) -> 900000 | ... N21: =SUM(N19:N20) -> 760000 | O21: =N21 -> 760000

Sheet Budget vs Actual
B2: Particulars | C2: Budget | D2: Actual | E2: Variance | F2: Variance %
B3: Revenue | C3: ='Revenue MIS'!C34 -> 6171250 | D3: ='P&L'!O3 -> 6450000 | E3: =D3-C3 -> 278750 | F3: =E3/C3 -> 0.045169131
B4: Operating Expenses | C4: =-SUM('Expense MIS'!C25:C40) -> -1438186.4 | D4: ='P&L'!O8 -> -600106.55 | E4: =D4-C4 -> 838079.84 | F4: =E4/C4 -> -0.58273381
B5: EBITDA | C5: =SUM(C3:C4) -> 4733063.6 | D5: =SUM(D3:D4) -> 5849893.4 | E5: =D5-C5 -> 1116829.8 | F5: =E5/C5 -> 0.23596341
B7: Financial Expenses | C7: =-SUM('Expense MIS'!C37:C38) -> -68287.987 | D7: ='P&L'!O12 -> -75875.541 | E7: =D7-C7 -> -7587.5541 | F7: =E7/C7 -> 0.11111111
B8: Depreciation | C8: =-'Expense MIS'!C39 -> -124159.98 | D8: ='P&L'!O13 -> -137955.53 | E8: =D8-C8 -> -13795.553 | F8: =E8/C8 -> 0.11111111
B9: Profit Before Tax | C9: =SUM(C5:C8) -> 4540615.6 | D9: =SUM(D5:D8) -> 5636062.4 | E9: =D9-C9 -> 1095446.7 | F9: =E9/C9 -> 0.24125511
B11: Tax Provision | C11: =-'Expense MIS'!C41 -> -1438186.4 | D11: ='P&L'!O16 -> -137955.53 | E11: =D11-C11 -> 1300230.9 | F11: =E11/C11 -> -0.90407674
B12: Net Profit | C12: =SUM(C9:C11) -> 3102429.2 | D12: =SUM(D9:D11) -> 5498106.8 | E12: =D12-C12 -> 2395677.6 | F12: =E12/C12 -> 0.77219412
B14: Closing Cash Balance | C14: 600000 | D14: =CFS!O21 -> 760000 | E14: =D14-C14 -> 160000 | F14: =E14/C14 -> 0.26666667

Sheet Receivables & Payables Tracker
B2: ACCOUNTS RECEIVABLE
B4: Customer Name | C4: Outstanding Amount | D4: Status
B5: A | C5: 10000 | D5: Outstanding
B6: B | C6: 20000 | D6: Partially Received
B7: C | C7: 30000 | D7: Received
B15: Total | C15: =SUM(C5:C14) -> 60000 | G15: SUMMARY
G17: Particulars | H17: Amount
B18: ACCOUNTS PAYABLE | G18: Total Receivables | H18: =C15 -> 60000
G19: Total Payables | H19: =C31 -> 30000
B20: Vendor Name | C20: Outstanding Amount | D20: Status | G20: Net Working Capital Position | H20: =H18-H19 -> 30000
B21: X | C21: 5000 | D21: Outstanding
B22: Y | C22: 10000 | D22: Partially Paid
B23: Z | C23: 15000 | D23: Paid
B31: Total | C31: =SUM(C21:C30) -> 30000

Sheet Working Capital Inputs
B2: Particulars | C2: Amount
B3: Cash & Bank Balance | C3: =CFS!O21 -> 760000
B4: Accounts Receivable | C4: ='Receivables & Payables Tracker'!H18 -> 60000
B5: Inventory | C5: 100000
B6: Other Current Assets | C6: 50000
B7: Total Current Assets | C7: =SUM(C3:C6) -> 970000
B9: Accounts Payable | C9: ='Receivables & Payables Tracker'!H19 -> 30000
B10: Short-Term Borrowings | C10: 300000
B11: Other Current Liabilities | C11: 150000
B12: Total Current Liabilities | C12: =SUM(C9:C11) -> 480000
B14: Working Capital | C14: =C7-C12 -> 490000
B15: Current Ratio | C15: =C7/C12 -> 2.0208333
B16: Quick Ratio | C16: =(C7-C5)/C12 -> 1.8125

Sheet KPI & Ratio Analysis
B2: GENERAL KPIs / RATIOS
B4: KPI / Ratio | C4: Value
B5: Financial KPIs:
B6: Revenue Growth % | C6: ='P&L'!O3/'Revenue MIS'!C2-1 -> 0.29
B7: Gross Margin % | C7: ='P&L'!O6 -> 0.84600313
B8: EBITDA Margin % | C8: ='P&L'!O10 -> 0.75296335
B9: Net Profit Margin % | C9: ='P&L'!O18 -> 0.6984228
B10: Operating Expense Ratio % | C10: =-('P&L'!O8/'P&L'!O3) -> 0.093039776
B11: Cash Balance | C11: =CFS!O21 -> 760000
B12: Burn Rate | C12: =ABS(CFS!O7)/12 -> 5000
B13: Runway (Months) | C13: =CFS!O21/'KPI & Ratio Analysis'!C12 -> 152
B15: Liquidity Ratios:
B16: Current Ratio | C16: ='Working Capital Inputs'!C15 -> 2.0208333
B17: Quick Ratio | C17: ='Working Capital Inputs'!C16 -> 1.8125
B20: INDUSTRY-SPECIFIC KPIs / RATIOS
B22: Particulars | C22: Value
B23: Production Quantity | C23: ='Manufacturing Metrics'!C3 -> 100000
B24: Capacity Utilization % | C24: ='Manufacturing Metrics'!C10 -> 0.83333333
B25: Sales Realization per Unit | C25: ='Manufacturing Metrics'!C11 -> 70.108696
B26: Defect Rate % | C26: ='Manufacturing Metrics'!C12 -> 0.025
B27: Production Efficiency % | C27: ='Manufacturing Metrics'!C13 -> 0.92
