Workbook

Sheet Instructions
C2: → Manual Input Required
B4: STARTUP MIS TEMPLATE FOR D2C / ECOMMERCE BUSINESS — INSTRUCTIONS FOR USE
B6: GENERAL INSTRUCTIONS
B8: • Cells highlighted in Light Blue are designated for manual data entry unless otherwise specified.
B9: • While entering numerical values, do not use commas (,) or negative signs (-) unless specifically instructed.
B10: • All other cells contain formulas and should not be modified.
B11: • It is recommended to update all relevant input sheets before reviewing the Dashboard and KPI outputs.
B13: DASHBOARD SHEET
B15: The only manual inputs required in this sheet are the following fields under the Basic Details section:
B17: • Company Name
B18: • Industry
B19: • Reporting Month
B20: • Prepared By
... B117: Please ensure all relevant data has been updated before reviewing the outputs.

Sheet Dashboard
D2: Company Name | E2: ABC Pvt Ltd
D3: Industry | E3: D2C
D4: Reporting Month | E4: 46082
D5: Prepared By | E5: XXX
D8: MONTHLY MIS DASHBOARD
D10: Revenue | F10: EBITDA
D11: ='P&L'!O3 -> 6450000 | F11: ='P&L'!O5 -> 4470338.1
H12: Total Customers | J12: EBITDA Margin % | K12: ='KPI & Ratio Analysis'!C7 -> 0.69307568
H13: ='D2C Metrics'!C4 -> 8000 | J13: Net Margin % | K13: ='KPI & Ratio Analysis'!C8 -> 0.63853512
J14: Current Ratio | K14: ='KPI & Ratio Analysis'!C15 -> 2.0208333
D15: Net Profit | F15: Cash Balance | J15: Runway | K15: ='KPI & Ratio Analysis'!C12 -> 152
D16: ='P&L'!O13 -> 4118551.5 | F16: =CFS!O21 -> 760000

Sheet Revenue MIS
B2: Previous Year Revenue | C2: 5000000
B5: Month | C5: Website Sales | D5: Marketplace Sales | E5: Offline Sales | F5: B2B Sales | G5: Other Revenue | H5: Total Revenue | I5: Growth %
B6: Apr | C6: 100000 | D6: 90000 | E6: 80000 | F6: 70000 | G6: 60000 | H6: =SUM(C6:G6) -> 400000
B7: May | C7: 105000 | D7: 95000 | E7: 85000 | F7: 75000 | G7: 65000 | H7: =SUM(C7:G7) -> 425000 | I7: =H7/H6-1 -> 0.0625
B8: Jun | C8: 110000 | D8: 100000 | E8: 90000 | F8: 80000 | G8: 70000 | H8: =SUM(C8:G8) -> 450000 | I8: =H8/H7-1 -> 0.058823529
B9: Jul | C9: 115000 | D9: 105000 | E9: 95000 | F9: 85000 | G9: 75000 | H9: =SUM(C9:G9) -> 475000 | I9: =H9/H8-1 -> 0.055555556
B10: Aug | C10: 120000 | D10: 110000 | E10: 100000 | F10: 90000 | G10: 80000 | H10: =SUM(C10:G10) -> 500000 | I10: =H10/H9-1 -> 0.052631579
B11: Sep | C11: 125000 | D11: 115000 | E11: 105000 | F11: 95000 | G11: 85000 | H11: =SUM(C11:G11) -> 525000 | I11: =H11/H10-1 -> 0.05
B12: Oct | C12: 130000 | D12: 120000 | E12: 110000 | F12: 100000 | G12: 90000 | H12: =SUM(C12:G12) -> 550000 | I12: =H12/H11-1 -> 0.047619048
B13: Nov | C13: 135000 | D13: 125000 | E13: 115000 | F13: 105000 | G13: 95000 | H13: =SUM(C13:G13) -> 575000 | I13: =H13/H12-1 -> 0.045454545
B14: Dec | C14: 140000 | D14: 130000 | E14: 120000 | F14: 110000 | G14: 100000 | H14: =SUM(C14:G14) -> 600000 | I14: =H14/H13-1 -> 0.043478261
B15: Jan | C15: 145000 | D15: 135000 | E15: 125000 | F15: 115000 | G15: 105000 | H15: =SUM(C15:G15) -> 625000 | I15: =H15/H14-1 -> 0.041666667
B16: Feb | C16: 150000 | D16: 140000 | E16: 130000 | F16: 120000 | G16: 110000 | H16: =SUM(C16:G16) -> 650000 | I16: =H16/H15-1 -> 0.04
B17: Mar | C17: 155000 | D17: 145000 | E17: 135000 | F17: 125000 | G17: 115000 | H17: =SUM(C17:G17) -> 675000 | I17: =H17/H16-1 -> 0.038461538
B18: Total | C18: =SUM(C6:C17) -> 1530000 | D18: =SUM(D6:D17) -> 1410000 | E18: =SUM(E6:E17) -> 1290000 | F18: =SUM(F6:F17) -> 1170000 | G18: =SUM(G6:G17) -> 1050000 | H18: =SUM(H6:H17) -> 6450000
B21: Month | C21: Target Revenue | D21: Actual Revenue | E21: Variance | F21: Variance %
B22: Apr | C22: 320000 | D22: =H6 -> 400000 | E22: =D22-C22 -> 80000 | F22: =E22/C22 -> 0.25
B23: May | C23: 340000 | D23: =H7 -> 425000 | E23: =D23-C23 -> 85000 | F23: =E23/C23 -> 0.25
B24: Jun | C24: 405000 | D24: =H8 -> 450000 | E24: =D24-C24 -> 45000 | F24: =E24/C24 -> 0.11111111
B25: Jul | C25: 522500 | D25: =H9 -> 475000 | E25: =D25-C25 -> -47500 | F25: =E25/C25 -> -0.090909091
B26: Aug | C26: 550000 | D26: =H10 -> 500000 | E26: =D26-C26 -> -50000 | F26: =E26/C26 -> -0.090909091
B27: Sep | C27: 630000 | D27: =H11 -> 525000 | E27: =D27-C27 -> -105000 | F27: =E27/C27 -> -0.16666667
B28: Oct | C28: 550000 | D28: =H12 -> 550000 | E28: =D28-C28 -> 0 | F28: =E28/C28 -> 0
B29: Nov | C29: 431250 | D29: =H13 -> 575000 | E29: =D29-C29 -> 143750 | F29: =E29/C29 -> 0.33333333
B30: Dec | C30: 420000 | D30: =H14 -> 600000 | E30: =D30-C30 -> 180000 | F30: =E30/C30 -> 0.42857143
B31: Jan | C31: 312500 | D31: =H15 -> 625000 | E31: =D31-C31 -> 312500 | F31: =E31/C31 -> 1
B32: Feb | C32: 812500 | D32: =H16 -> 650000 | E32: =D32-C32 -> -162500 | F32: =E32/C32 -> -0.2
B33: Mar | C33: 877500 | D33: =H17 -> 675000 | E33: =D33-C33 -> -202500 | F33: =E33/C33 -> -0.23076923
B34: Total | C34: =SUM(C22:C33) -> 6171250 | D34: =SUM(D22:D33) -> 6450000 | E34: =SUM(E22:E33) -> 278750

Sheet Expense MIS
B2: Expense Head | C2: Apr | D2: May | E2: Jun | F2: Jul | G2: Aug | H2: Sep | I2: Oct | J2: Nov | K2: Dec | L2: Jan | M2: Feb | N2: Mar | O2: Total
B3: Salaries & Wages | C3: 25000 | D3: 25625 | E3: 26265.625 | F3: 26922.266 | G3: 27595.322 | H3: 28285.205 | I3: 28992.335 | J3: 29717.144 | K3: 30460.072 | L3: 31221.574 | M3: 32002.114 | N3: 32802.166 | O3: =SUM(C3:N3) -> 344888.82
B4: Inventory Purchases | C4: 40000 | D4: 41000 | E4: 42025 | F4: 43075.625 | G4: 44152.516 | H4: 45256.329 | I4: 46387.737 | J4: 47547.43 | K4: 48736.116 | L4: 49954.519 | M4: 51203.382 | N4: 52483.466 | O4: =SUM(C4:N4) -> 551822.12
B5: Marketplace Fees | C5: 2000 | D5: 2050 | E5: 2101.25 | F5: 2153.7812 | G5: 2207.6258 | H5: 2262.8164 | I5: 2319.3868 | J5: 2377.3715 | K5: 2436.8058 | L5: 2497.7259 | M5: 2560.1691 | N5: 2624.1733 | O5: =SUM(C5:N5) -> 27591.106
B6: Warehousing Costs | C6: 5000 | D6: 5125 | E6: 5253.125 | F6: 5384.4531 | G6: 5519.0645 | H6: 5657.0411 | I6: 5798.4671 | J6: 5943.4288 | K6: 6092.0145 | L6: 6244.3148 | M6: 6400.4227 | N6: 6560.4333 | O6: =SUM(C6:N6) -> 68977.765
B7: Rent | C7: 10000 | D7: 10250 | E7: 10506.25 | F7: 10768.906 | G7: 11038.129 | H7: 11314.082 | I7: 11596.934 | J7: 11886.858 | K7: 12184.029 | L7: 12488.63 | M7: 12800.845 | N7: 13120.867 | O7: =SUM(C7:N7) -> 137955.53
B8: Marketing | C8: 10000 | D8: 10250 | E8: 10506.25 | F8: 10768.906 | G8: 11038.129 | H8: 11314.082 | I8: 11596.934 | J8: 11886.858 | K8: 12184.029 | L8: 12488.63 | M8: 12800.845 | N8: 13120.867 | O8: =SUM(C8:N8) -> 137955.53
B9: Software Subscriptions | C9: 5000 | D9: 5125 | E9: 5253.125 | F9: 5384.4531 | G9: 5519.0645 | H9: 5657.0411 | I9: 5798.4671 | J9: 5943.4288 | K9: 6092.0145 | L9: 6244.3148 | M9: 6400.4227 | N9: 6560.4333 | O9: =SUM(C9:N9) -> 68977.765
B10: Utilities | C10: 3000 | D10: 3075 | E10: 3151.875 | F10: 3230.6719 | G10: 3311.4387 | H10: 3394.2246 | I10: 3479.0803 | J10: 3566.0573 | K10: 3655.2087 | L10: 3746.5889 | M10: 3840.2536 | N10: 3936.26 | O10: =SUM(C10:N10) -> 41386.659
B11: Internet & Phone | C11: 1000 | D11: 1025 | E11: 1050.625 | F11: 1076.8906 | G11: 1103.8129 | H11: 1131.4082 | I11: 1159.6934 | J11: 1188.6858 | K11: 1218.4029 | L11: 1248.863 | M11: 1280.0845 | N11: 1312.0867 | O11: =SUM(C11:N11) -> 13795.553
B12: Travel | C12: 5000 | D12: 5125 | E12: 5253.125 | F12: 5384.4531 | G12: 5519.0645 | H12: 5657.0411 | I12: 5798.4671 | J12: 5943.4288 | K12: 6092.0145 | L12: 6244.3148 | M12: 6400.4227 | N12: 6560.4333 | O12: =SUM(C12:N12) -> 68977.765
B13: Office Expenses | C13: 3000 | D13: 3075 | E13: 3151.875 | F13: 3230.6719 | G13: 3311.4387 | H13: 3394.2246 | I13: 3479.0803 | J13: 3566.0573 | K13: 3655.2087 | L13: 3746.5889 | M13: 3840.2536 | N13: 3936.26 | O13: =SUM(C13:N13) -> 41386.659
B14: Professional Fees | C14: 5000 | D14: 5125 | E14: 5253.125 | F14: 5384.4531 | G14: 5519.0645 | H14: 5657.0411 | I14: 5798.4671 | J14: 5943.4288 | K14: 6092.0145 | L14: 6244.3148 | M14: 6400.4227 | N14: 6560.4333 | O14: =SUM(C14:N14) -> 68977.765
... B20: Provision for Tax | C20: 10000 | D20: 10250 | E20: 10506.25 | F20: 10768.906 | G20: 11038.129 | H20: 11314.082 | I20: 11596.934 | J20: 11886.858 | K20: 12184.029 | L20: 12488.63 | M20: 12800.845 | N20: 13120.867 | O20: =SUM(C20:N20) -> 137955.53
B21: Total Expenses | C21: =SUM(C3:C20) -> 143500 | D21: =SUM(D3:D20) -> 147087.5 | E21: =SUM(E3:E20) -> 150764.69 | F21: =SUM(F3:F20) -> 154533.8 | G21: =SUM(G3:G20) -> 158397.15 | H21: =SUM(H3:H20) -> 162357.08 | I21: =SUM(I3:I20) -> 166416.01 | J21: =SUM(J3:J20) -> 170576.41 | ... N21: =SUM(N3:N20) -> 188284.44 | O21: =SUM(C21:N21) -> 1979661.9
B24: Expense Head | C24: Budget | D24: Actual | E24: Variance | F24: Variance %
B25: Salaries & Wages | C25: 310399.94 | D25: =O3 -> 344888.82 | E25: =D25-C25 -> 34488.882 | F25: =E25/C25 -> 0.11111111
B26: Inventory Purchases | C26: 441457.7 | D26: =O4 -> 551822.12 | E26: =D26-C26 -> 110364.42 | F26: =E26/C26 -> 0.25
B27: Marketplace Fees | C27: 19313.774 | D27: =O5 -> 27591.106 | E27: =D27-C27 -> 8277.3318 | F27: =E27/C27 -> 0.42857143
B28: Warehousing Costs | C28: 75875.541 | D28: =O6 -> 68977.765 | E28: =D28-C28 -> -6897.7765 | F28: =E28/C28 -> -0.090909091
B29: Rent | C29: 165546.64 | D29: =O7 -> 137955.53 | E29: =D29-C29 -> -27591.106 | F29: =E29/C29 -> -0.16666667
B30: Marketing | C30: 179342.19 | D30: =O8 -> 137955.53 | E30: =D30-C30 -> -41386.659 | F30: =E30/C30 -> -0.23076923
B31: Software Subscriptions | C31: 62079.988 | D31: =O9 -> 68977.765 | E31: =D31-C31 -> 6897.7765 | F31: =E31/C31 -> 0.11111111
B32: Utilities | C32: 33109.327 | D32: =O10 -> 41386.659 | E32: =D32-C32 -> 8277.3318 | F32: =E32/C32 -> 0.25
B33: Internet & Phone | C33: 9656.8871 | D33: =O11 -> 13795.553 | E33: =D33-C33 -> 4138.6659 | F33: =E33/C33 -> 0.42857143
B34: Travel | C34: 75875.541 | D34: =O12 -> 68977.765 | E34: =D34-C34 -> -6897.7765 | F34: =E34/C34 -> -0.090909091
B35: Office Expenses | C35: 49663.991 | D35: =O13 -> 41386.659 | E35: =D35-C35 -> -8277.3318 | F35: =E35/C35 -> -0.16666667
B36: Professional Fees | C36: 89671.094 | D36: =O14 -> 68977.765 | E36: =D36-C36 -> -20693.329 | F36: =E36/C36 -> -0.23076923
... B42: Provision for Tax | C42: 124159.98 | D42: =O20 -> 137955.53 | E42: =D42-C42 -> 13795.553 | F42: =E42/C42 -> 0.11111111
B43: Total | C43: =SUM(C25:C42) -> 1878264.5 | D43: =SUM(D25:D42) -> 1979661.9 | E43: =SUM(E25:E42) -> 101397.31

Sheet D2C Metrics
B2: Particulars | C2: Value
B3: Total Orders | C3: 12000
B4: Total Customers | C4: 8000
B5: Returned Orders | C5: 600
B6: Marketing Spend | C6: ='Expense MIS'!$O$8 -> 137955.53
B9: Particulars | C9: Value
B10: Average Order Value (AOV) | C10: ='Revenue MIS'!H18/'D2C Metrics'!C3 -> 537.5
B11: Customer Acquisition Cost (CAC) | C11: ='Expense MIS'!O8/'D2C Metrics'!C4 -> 17.244441
B12: Return Rate | C12: =C5/C3 -> 0.05
B13: Revenue per Customer | C13: ='Revenue MIS'!H18/'D2C Metrics'!C4 -> 806.25

Sheet P&L
B2: Particulars | C2: Apr | D2: May | E2: Jun | F2: Jul | G2: Aug | H2: Sep | I2: Oct | J2: Nov | K2: Dec | L2: Jan | M2: Feb | N2: Mar | O2: Total
B3: Total Revenue | C3: {=TRANSPOSE('Revenue MIS'!H6:H17)} -> 400000 | D3: 425000 | E3: 450000 | F3: 475000 | G3: 500000 | H3: 525000 | I3: 550000 | J3: 575000 | K3: 600000 | L3: 625000 | M3: 650000 | N3: 675000 | O3: =SUM(C3:N3) -> 6450000
B4: Total Expenses | C4: =-'Expense MIS'!C21 -> -143500 | D4: =-'Expense MIS'!D21 -> -147087.5 | E4: =-'Expense MIS'!E21 -> -150764.69 | F4: =-'Expense MIS'!F21 -> -154533.8 | G4: =-'Expense MIS'!G21 -> -158397.15 | H4: =-'Expense MIS'!H21 -> -162357.08 | I4: =-'Expense MIS'!I21 -> -166416.01 | J4: =-'Expense MIS'!J21 -> -170576.41 | ... N4: =-'Expense MIS'!N21 -> -188284.44 | O4: =SUM(C4:N4) -> -1979661.9
B5: EBITDA | C5: =SUM(C3:C4) -> 256500 | D5: =SUM(D3:D4) -> 277912.5 | E5: =SUM(E3:E4) -> 299235.31 | F5: =SUM(F3:F4) -> 320466.2 | G5: =SUM(G3:G4) -> 341602.85 | H5: =SUM(H3:H4) -> 362642.92 | I5: =SUM(I3:I4) -> 383583.99 | J5: =SUM(J3:J4) -> 404423.59 | ... N5: =SUM(N3:N4) -> 486715.56 | O5: =SUM(C5:N5) -> 4470338.1
B6: EBITDA Margin % | C6: =C5/C3 -> 0.64125 | D6: =D5/D3 -> 0.65391176 | E6: =E5/E3 -> 0.66496736 | F6: =F5/F3 -> 0.67466567 | G6: =G5/G3 -> 0.6832057 | H6: =H5/H3 -> 0.69074842 | I6: =I5/I3 -> 0.69742544 | J6: =J5/J3 -> 0.70334538 | ... O6: =O5/O3 -> 0.69307568
B8: Interest & Bank Charges | C8: =-SUM('Expense MIS'!C$17:C$18) -> -5500 | D8: =-SUM('Expense MIS'!D$17:D$18) -> -5637.5 | E8: =-SUM('Expense MIS'!E$17:E$18) -> -5778.4375 | F8: =-SUM('Expense MIS'!F$17:F$18) -> -5922.8984 | G8: =-SUM('Expense MIS'!G$17:G$18) -> -6070.9709 | H8: =-SUM('Expense MIS'!H$17:H$18) -> -6222.7452 | I8: =-SUM('Expense MIS'!I$17:I$18) -> -6378.3138 | J8: =-SUM('Expense MIS'!J$17:J$18) -> -6537.7716 | ... N8: =-SUM('Expense MIS'!N$17:N$18) -> -7216.4766 | O8: =SUM(C8:N8) -> -75875.541
B9: Depreciation & Amortization | C9: =-'Expense MIS'!C$19 -> -10000 | D9: =-'Expense MIS'!D$19 -> -10250 | E9: =-'Expense MIS'!E$19 -> -10506.25 | F9: =-'Expense MIS'!F$19 -> -10768.906 | G9: =-'Expense MIS'!G$19 -> -11038.129 | H9: =-'Expense MIS'!H$19 -> -11314.082 | I9: =-'Expense MIS'!I$19 -> -11596.934 | J9: =-'Expense MIS'!J$19 -> -11886.858 | ... N9: =-'Expense MIS'!N$19 -> -13120.867 | O9: =SUM(C9:N9) -> -137955.53
B10: Profit Before Tax (PBT) | C10: =SUM(C5,C8:C9) -> 241000 | D10: =SUM(D5,D8:D9) -> 262025 | E10: =SUM(E5,E8:E9) -> 282950.62 | F10: =SUM(F5,F8:F9) -> 303774.39 | G10: =SUM(G5,G8:G9) -> 324493.75 | H10: =SUM(H5,H8:H9) -> 345106.09 | I10: =SUM(I5,I8:I9) -> 365608.75 | J10: =SUM(J5,J8:J9) -> 385998.97 | ... N10: =SUM(N5,N8:N9) -> 466378.22 | O10: =SUM(C10:N10) -> 4256507.1
B12: Tax Expense | C12: =-'Expense MIS'!C$20 -> -10000 | D12: =-'Expense MIS'!D$20 -> -10250 | E12: =-'Expense MIS'!E$20 -> -10506.25 | F12: =-'Expense MIS'!F$20 -> -10768.906 | G12: =-'Expense MIS'!G$20 -> -11038.129 | H12: =-'Expense MIS'!H$20 -> -11314.082 | I12: =-'Expense MIS'!I$20 -> -11596.934 | J12: =-'Expense MIS'!J$20 -> -11886.858 | ... N12: =-'Expense MIS'!N$20 -> -13120.867 | O12: =SUM(C12:N12) -> -137955.53
B13: Net Profit | C13: =SUM(C10,C12) -> 231000 | D13: =SUM(D10,D12) -> 251775 | E13: =SUM(E10,E12) -> 272444.38 | F13: =SUM(F10,F12) -> 293005.48 | G13: =SUM(G10,G12) -> 313455.62 | H13: =SUM(H10,H12) -> 333792.01 | I13: =SUM(I10,I12) -> 354011.81 | J13: =SUM(J10,J12) -> 374112.11 | ... N13: =SUM(N10,N12) -> 453257.35 | O13: =SUM(C13:N13) -> 4118551.5
B14: Net Margin % | C14: =C13/C3 -> 0.5775 | D14: =D13/D3 -> 0.59241176 | E14: =E13/E3 -> 0.60543194 | F14: =F13/F3 -> 0.61685365 | G14: =G13/G3 -> 0.62691124 | H14: =H13/H3 -> 0.63579431 | I14: =I13/I3 -> 0.64365784 | J14: =J13/J3 -> 0.65062975 | ... O14: =O13/O3 -> 0.63853512

Sheet CFS
B2: Particulars | C2: Apr | D2: May | E2: Jun | F2: Jul | G2: Aug | H2: Sep | I2: Oct | J2: Nov | K2: Dec | L2: Jan | M2: Feb | N2: Mar | O2: Total
B3: Cash Received from Customers | C3: 200000 | D3: =C3+5000 -> 205000 | E3: =D3+5000 -> 210000 | F3: =E3+5000 -> 215000 | G3: =F3+5000 -> 220000 | H3: =G3+5000 -> 225000 | I3: =H3+5000 -> 230000 | J3: =I3+5000 -> 235000 | K3: =J3+5000 -> 240000 | ... N3: =M3+5000 -> 255000 | O3: =SUM(C3:N3) -> 2730000
B4: Payments to Suppliers | C4: -100000 | D4: =C4-5000 -> -105000 | E4: =D4-5000 -> -110000 | F4: =E4-5000 -> -115000 | G4: =F4-5000 -> -120000 | H4: =G4-5000 -> -125000 | I4: =H4-5000 -> -130000 | J4: =I4-5000 -> -135000 | K4: =J4-5000 -> -140000 | ... N4: =M4-5000 -> -155000 | O4: =SUM(C4:N4) -> -1530000
B5: Salary Payments | C5: -10000 | D5: =C5-5000 -> -15000 | E5: =D5-5000 -> -20000 | F5: =E5-5000 -> -25000 | G5: =F5-5000 -> -30000 | H5: =G5-5000 -> -35000 | I5: =H5-5000 -> -40000 | J5: =I5-5000 -> -45000 | K5: =J5-5000 -> -50000 | ... N5: =M5-5000 -> -65000 | O5: =SUM(C5:N5) -> -450000
B6: Operating Expenses Paid | C6: -30000 | D6: =C6-5000 -> -35000 | E6: =D6-5000 -> -40000 | F6: =E6-5000 -> -45000 | G6: =F6-5000 -> -50000 | H6: =G6-5000 -> -55000 | I6: =H6-5000 -> -60000 | J6: =I6-5000 -> -65000 | K6: =J6-5000 -> -70000 | ... N6: =M6-5000 -> -85000 | O6: =SUM(C6:N6) -> -690000
B7: Net Cash from Operations | C7: =SUM(C3:C6) -> 60000 | D7: =SUM(D3:D6) -> 50000 | E7: =SUM(E3:E6) -> 40000 | F7: =SUM(F3:F6) -> 30000 | G7: =SUM(G3:G6) -> 20000 | H7: =SUM(H3:H6) -> 10000 | I7: =SUM(I3:I6) -> 0 | J7: =SUM(J3:J6) -> -10000 | ... N7: =SUM(N3:N6) -> -50000 | O7: =SUM(C7:N7) -> 60000
B9: Purchase of Equipment | C9: -250000 | O9: =SUM(C9:N9) -> -250000
B10: Purchase of Assets | H10: -100000 | O10: =SUM(C10:N10) -> -100000
B11: Net Cash from Investing | C11: =SUM(C9:C10) -> -250000 | D11: =SUM(D9:D10) -> 0 | E11: =SUM(E9:E10) -> 0 | F11: =SUM(F9:F10) -> 0 | G11: =SUM(G9:G10) -> 0 | H11: =SUM(H9:H10) -> -100000 | I11: =SUM(I9:I10) -> 0 | J11: =SUM(J9:J10) -> 0 | ... N11: =SUM(N9:N10) -> 0 | O11: =SUM(C11:N11) -> -350000
B13: Capital Introduced | C13: 1000000 | O13: =SUM(C13:N13) -> 1000000
B14: Loan Received | C14: 500000 | O14: =SUM(C14:N14) -> 500000
B15: Loan Repayment | D15: -100000 | E15: -100000 | F15: -100000 | G15: -100000 | H15: -100000 | O15: =SUM(C15:N15) -> -500000
B16: Interest Paid | D16: -10000 | E16: -10000 | F16: -10000 | G16: -10000 | H16: -10000 | O16: =SUM(C16:N16) -> -50000
B17: Net Cash from Financing | C17: =SUM(C13:C16) -> 1500000 | D17: =SUM(D13:D16) -> -110000 | E17: =SUM(E13:E16) -> -110000 | F17: =SUM(F13:F16) -> -110000 | G17: =SUM(G13:G16) -> -110000 | H17: =SUM(H13:H16) -> -110000 | I17: =SUM(I13:I16) -> 0 | J17: =SUM(J13:J16) -> 0 | ... N17: =SUM(N13:N16) -> 0 | O17: =SUM(C17:N17) -> 950000
B19: Opening Cash & Cash Equivalents | C19: 100000 | D19: =C21 -> 1410000 | E19: =D21 -> 1350000 | F19: =E21 -> 1280000 | G19: =F21 -> 1200000 | H19: =G21 -> 1110000 | I19: =H21 -> 910000 | J19: =I21 -> 910000 | K19: =J21 -> 900000 | ... N19: =M21 -> 810000 | O19: =C19 -> 100000
B20: Change in Cash & Cash Equivalents | C20: =SUM(C7,C11,C17) -> 1310000 | D20: =SUM(D7,D11,D17) -> -60000 | E20: =SUM(E7,E11,E17) -> -70000 | F20: =SUM(F7,F11,F17) -> -80000 | G20: =SUM(G7,G11,G17) -> -90000 | H20: =SUM(H7,H11,H17) -> -200000 | I20: =SUM(I7,I11,I17) -> 0 | J20: =SUM(J7,J11,J17) -> -10000 | ... N20: =SUM(N7,N11,N17) -> -50000 | O20: =SUM(C20:N20) -> 660000
B21: Closing Cash & Cash Equivalents | C21: =SUM(C19:C20) -> 1410000 | D21: =SUM(D19:D20) -> 1350000 | E21: =SUM(E19:E20) -> 1280000 | F21: =SUM(F19:F20) -> 1200000 | G21: =SUM(G19:G20) -> 1110000 | H21: =SUM(H19:H20) -> 910000 | I21: =SUM(I19:I20) -> 910000 | J21: =SUM(J19:J20) -> 900000 | ... N21: =SUM(N19:N20) -> 760000 | O21: =N21 -> 760000

Sheet Budget vs Actual
B2: Particulars | C2: Budget | D2: Actual | E2: Variance | F2: Variance %
B3: Revenue | C3: ='Revenue MIS'!C34 -> 6171250 | D3: ='P&L'!O3 -> 6450000 | E3: =D3-C3 -> 278750 | F3: =E3/C3 -> 0.045169131
B4: Operating Expenses | C4: =-SUM('Expense MIS'!C25:C38) -> -1561656.6 | D4: ='P&L'!O4 -> -1979661.9 | E4: =D4-C4 -> -418005.25 | F4: =E4/C4 -> 0.26766784
B5: EBITDA | C5: =SUM(C3:C4) -> 4609593.4 | D5: =SUM(D3:D4) -> 4470338.1 | E5: =D5-C5 -> -139255.25 | F5: =E5/C5 -> -0.030209878
B7: Financial Expenses | C7: =-SUM('Expense MIS'!C39:C40) -> -68287.987 | D7: ='P&L'!O8 -> -75875.541 | E7: =D7-C7 -> -7587.5541 | F7: =E7/C7 -> 0.11111111
B8: Depreciation | C8: =-'Expense MIS'!C41 -> -124159.98 | D8: ='P&L'!O9 -> -137955.53 | E8: =D8-C8 -> -13795.553 | F8: =E8/C8 -> 0.11111111
B9: Profit Before Tax | C9: =SUM(C5:C8) -> 4417145.4 | D9: =SUM(D5:D8) -> 4256507.1 | E9: =D9-C9 -> -160638.36 | F9: =E9/C9 -> -0.036367008
B11: Tax Provision | C11: =-'Expense MIS'!C43 -> -1878264.5 | D11: ='P&L'!O12 -> -137955.53 | E11: =D11-C11 -> 1740309 | F11: =E11/C11 -> -0.9265516
B12: Net Profit | C12: =SUM(C9:C11) -> 2538880.9 | D12: =SUM(D9:D11) -> 4118551.5 | E12: =D12-C12 -> 1579670.6 | F12: =E12/C12 -> 0.62219171
B14: Closing Cash Balance | C14: 600000 | D14: =CFS!O21 -> 760000 | E14: =D14-C14 -> 160000 | F14: =E14/C14 -> 0.26666667

Sheet Receivables & Payables Tracker
B2: ACCOUNTS RECEIVABLE
B4: Customer Name | C4: Outstanding Amount | D4: Status
B5: A | C5: 10000 | D5: Outstanding
B6: B | C6: 20000 | D6: Outstanding
B7: C | C7: 30000 | D7: Received
B15: Total | C15: =SUM(C5:C14) -> 60000 | G15: SUMMARY
G17: Particulars | H17: Amount
B18: ACCOUNTS PAYABLE | G18: Total Receivables | H18: =C15 -> 60000
G19: Total Payables | H19: =C31 -> 30000
B20: Vendor Name | C20: Outstanding Amount | D20: Status | G20: Net Working Capital Position | H20: =H18-H19 -> 30000
B21: X | C21: 5000 | D21: Outstanding
B22: Y | C22: 10000 | D22: Partially Paid
B23: Z | C23: 15000 | D23: Paid
B31: Total | C31: =SUM(C21:C30) -> 30000

Sheet Working Capital Inputs
B2: Particulars | C2: Amount
B3: Cash & Bank Balance | C3: =CFS!O21 -> 760000
B4: Accounts Receivable | C4: ='Receivables & Payables Tracker'!H18 -> 60000
B5: Inventory | C5: 100000
B6: Other Current Assets | C6: 50000
B7: Total Current Assets | C7: =SUM(C3:C6) -> 970000
B9: Accounts Payable | C9: ='Receivables & Payables Tracker'!H19 -> 30000
B10: Short-Term Borrowings | C10: 300000
B11: Other Current Liabilities | C11: 150000
B12: Total Current Liabilities | C12: =SUM(C9:C11) -> 480000
B14: Working Capital | C14: =C7-C12 -> 490000
B15: Current Ratio | C15: =C7/C12 -> 2.0208333
B16: Quick Ratio | C16: =(C7-C5)/C12 -> 1.8125

Sheet KPI & Ratio Analysis
B2: GENERAL KPIs / RATIOS
B4: KPI / Ratio | C4: Value
B5: Financial KPIs:
B6: Revenue Growth % | C6: ='P&L'!O3/'Revenue MIS'!C2-1 -> 0.29
B7: EBITDA Margin % | C7: ='P&L'!O6 -> 0.69307568
B8: Net Profit Margin % | C8: ='P&L'!O14 -> 0.63853512
B9: Operating Expense Ratio % | C9: =-('P&L'!O4/'P&L'!O3) -> 0.30692432
B10: Cash Balance | C10: =CFS!O21 -> 760000
B11: Burn Rate | C11: =ABS(CFS!O7)/12 -> 5000
B12: Runway (Months) | C12: =CFS!O21/'KPI & Ratio Analysis'!C11 -> 152
B14: Liquidity Ratios:
B15: Current Ratio | C15: ='Working Capital Inputs'!C15 -> 2.0208333
B16: Quick Ratio | C16: ='Working Capital Inputs'!C16 -> 1.8125
B19: INDUSTRY-SPECIFIC KPIs / RATIOS
B21: Particulars | C21: Value
B22: Total Customers | C22: ='D2C Metrics'!C4 -> 8000
B23: Average Order Value (AOV) | C23: ='D2C Metrics'!C10 -> 537.5
B24: Customer Acquisition Cost (CAC) | C24: ='D2C Metrics'!C11 -> 17.244441
B25: Return Rate | C25: ='D2C Metrics'!C12 -> 0.05
B26: Revenue per Customer | C26: ='D2C Metrics'!C13 -> 806.25
