Workbook

Sheet Instructions
B2: Step-by-Step Instructions
B4: Steps | C4: Details
B5: 1 | C5: Open the “Cover” sheet and fill in company name, analyst, and reporting details
B6: 2 | C6: Set projection, revenue, margin, working-capital, CapEx, WACC, and terminal assumptions on “Assumptions”
B7: 3 | C7: Review the “Income Statement” — projections flow from your assumptions
B8: 4 | C8: Check the “FCF Build” sheet where free cash flow is derived
B9: 5 | C9: Read the valuation outputs (EV and Equity Value) on the “DCF Valuation” sheet
B12: What Each Input Means
B14: Metric | E14: Description
B15: Revenue Growth (Year 1–5) | E15: Annual top-line growth rates driving the projection.
B16: Margin assumptions | E16: Gross, EBITDA, and EBIT margins plus tax rate applied to revenue.
B17: Working capital days | E17: Receivable, inventory, and payable days driving working-capital changes.
B18: WACC inputs | E18: Risk-free rate, risk premium, and beta feeding the discount rate.
B19: Terminal Growth Rate (g) | E19: Perpetual growth rate used in the Gordon Growth terminal value.
B20: Net Debt | E20: Subtracted from Enterprise Value to reach Equity Value.
B23: Important Guidelines
B25: Guideline | E25: Description
B26: Light Blue cells | E26: These are the cells to enter manual inputs by the user
B27: Keep g below WACC | E27: Terminal growth must be less than WACC or the model breaks.
B28: Sanity-check WACC | E28: Small WACC changes move valuation a lot — test a range.

Sheet Cover
B2: DISCOUNTED CASH FLOW (DCF) MODEL
B6: Comprehensive Valuation Template
B10: Company Name | C10: ABC Pvt Ltd
B12: Analyst | C12: ABC
B14: Date | C14: 46082
B16: Fiscal Year End | C16: 46082
B18: Currency | C18: INR
B20: Units | C20: 1000
B24: MODEL STRUCTURE
B26: Assumptions | C26: Key drivers, WACC inputs, terminal value
B27: Income Statement | C27: Historical & projected P&L
B28: FCF Build | C28: Free cash flow derivation
B29: DCF Valuation | C29: NPV, terminal value, Enterprice Value & Equity Value
B33: COLOR LEGEND
C35: → Manual input cell

Sheet Assumptions
B2: KEY ASSUMPTIONS
B4: PROJECTION HORIZON
B5: Projection Years | C5: 5
B6: Base Year (Historical) | C6: 2025
B7: First Projection Year | C7: 2026
B9: REVENUE ASSUMPTIONS
B10: Year 1 Revenue Growth | C10: 0.06
B11: Year 2 Revenue Growth | C11: 0.08
B12: Year 3 Revenue Growth | C12: 0.12
B13: Year 4 Revenue Growth | C13: 0.16
B14: Year 5 Revenue Growth | C14: 0.22
B16: MARGIN ASSUMPTIONS
B17: Gross Margin | C17: 0.45
B18: EBITDA Margin | C18: 0.22
B19: EBIT Margin | C19: 0.16
B20: Tax Rate | C20: 0.25
B22: WORKING CAPITAL ASSUMPTIONS
B23: Receivable Days | C23: 45
B24: Inventory Days | C24: 60
B25: Payable Days | C25: 40
B27: CAPEX & D&A ASSUMPTIONS
B28: CapEx as % of Revenue | C28: 0.05
B29: D&A as % of Revenue | C29: 0.04
B31: WACC ASSUMPTIONS
B32: Risk-Free Rate | C32: 0.07
B33: Risk Premium | C33: 0.06
B34: Beta | C34: 1.1
B35: Cost of Equity (CAPM) | C35: =C32+(C34*C33) -> 0.136
B36: WACC | C36: =C35 -> 0.136
B38: TERMINAL VALUE ASSUMPTIONS
B39: Terminal Growth Rate (g) | C39: 0.025
B40: Terminal Year EBITDA Multiple | C40: 8

Sheet Income Statement
B2: INCOME STATEMENT
C4: Actuals | F4: Projections
B5: Particulars | C5: 1 | D5: =C5+1 -> 2 | E5: =D5+1 -> 3 | F5: 1 | G5: =F5+1 -> 2 | H5: =G5+1 -> 3 | I5: =H5+1 -> 4 | J5: =I5+1 -> 5
B6: Revenue | C6: 800000 | D6: 850000 | E6: 920000 | F6: =E6*(1+Assumptions!C10) -> 975200 | G6: =F6*(1+Assumptions!C11) -> 1053216 | H6: =G6*(1+Assumptions!C12) -> 1179601.9 | I6: =H6*(1+Assumptions!C13) -> 1368338.2 | J6: =I6*(1+Assumptions!C14) -> 1669372.6
B7: Revenue Growth % | F7: =(F6-E6)/E6 -> 0.06 | G7: =(G6-F6)/F6 -> 0.08 | H7: =(H6-G6)/G6 -> 0.12 | I7: =(I6-H6)/H6 -> 0.16 | J7: =(J6-I6)/I6 -> 0.22
B8: Cost of Goods Sold (COGS) | C8: 420000 | D8: 490000 | E8: 560000 | F8: =D6*(1-Assumptions!$C$17) -> 467500 | G8: =E6*(1-Assumptions!$C$17) -> 506000 | H8: =F6*(1-Assumptions!$C$17) -> 536360 | I8: =G6*(1-Assumptions!$C$17) -> 579268.8 | J8: =H6*(1-Assumptions!$C$17) -> 648781.06
B9: Gross Profit | C9: =C6-C8 -> 380000 | D9: =D6-D8 -> 360000 | E9: =E6-E8 -> 360000 | F9: =F6-F8 -> 507700 | G9: =G6-G8 -> 547216 | H9: =H6-H8 -> 643241.92 | I9: =I6-I8 -> 789069.43 | J9: =J6-J8 -> 1020591.6
B10: Gross Margin % | C10: =IF(C6=0,"-",C9/C6) -> 0.475 | D10: =IF(D6=0,"-",D9/D6) -> 0.42352941 | E10: =IF(E6=0,"-",E9/E6) -> 0.39130435 | F10: =IF(F6=0,"-",F9/F6) -> 0.52061116 | G10: =IF(G6=0,"-",G9/G6) -> 0.51956674 | H10: =IF(H6=0,"-",H9/H6) -> 0.54530423 | I10: =IF(I6=0,"-",I9/I6) -> 0.57666256 | J10: =IF(J6=0,"-",J9/J6) -> 0.61136235
B11: Operating Expense | C11: 155 | D11: 170 | E11: 190 | F11: =D6*(Assumptions!$C$18-Assumptions!$C$29) -> 153000 | G11: =E6*(Assumptions!$C$18-Assumptions!$C$29) -> 165600 | H11: =F6*(Assumptions!$C$18-Assumptions!$C$29) -> 175536 | I11: =G6*(Assumptions!$C$18-Assumptions!$C$29) -> 189578.88 | J11: =H6*(Assumptions!$C$18-Assumptions!$C$29) -> 212328.35
B12: EBITDA | C12: =C9-C11 -> 379845 | D12: =D9-D11 -> 359830 | E12: =E9-E11 -> 359810 | F12: =F9-F11 -> 354700 | G12: =G9-G11 -> 381616 | H12: =H9-H11 -> 467705.92 | I12: =I9-I11 -> 599490.55 | J12: =J9-J11 -> 808263.24
B13: EBITDA Margin % | C13: =C12/C6 -> 0.47480625 | D13: =D12/D6 -> 0.42332941 | E13: =E12/E6 -> 0.39109783 | F13: =F12/F6 -> 0.36372026 | G13: =G12/G6 -> 0.36233403 | H13: =H12/H6 -> 0.39649471 | I13: =I12/I6 -> 0.43811576 | J13: =J12/J6 -> 0.48417185
B14: Depreciation & Amortization (D&A) | C14: =C6*Assumptions!$C$29 -> 32000 | D14: =D6*Assumptions!$C$29 -> 34000 | E14: =E6*Assumptions!$C$29 -> 36800 | F14: =F6*Assumptions!$C$29 -> 39008 | G14: =G6*Assumptions!$C$29 -> 42128.64 | H14: =H6*Assumptions!$C$29 -> 47184.077 | I14: =I6*Assumptions!$C$29 -> 54733.529 | J14: =J6*Assumptions!$C$29 -> 66774.905
B15: EBIT (Operating Income) | C15: =C12-C14 -> 347845 | D15: =D12-D14 -> 325830 | E15: =E12-E14 -> 323010 | F15: =F12-F14 -> 315692 | G15: =G12-G14 -> 339487.36 | H15: =H12-H14 -> 420521.84 | I15: =I12-I14 -> 544757.02 | J15: =J12-J14 -> 741488.33
B16: Interest Expense | C16: 2000 | D16: 2100 | E16: 2300 | F16: 2500 | G16: 2700 | H16: 2900 | I16: 3100 | J16: 3300
B17: EBT (Pre-Tax Income) | C17: =C15-C16 -> 345845 | D17: =D15-D16 -> 323730 | E17: =E15-E16 -> 320710 | F17: =F15-F16 -> 313192 | G17: =G15-G16 -> 336787.36 | H17: =H15-H16 -> 417621.84 | I17: =I15-I16 -> 541657.02 | J17: =J15-J16 -> 738188.33
B18: Income Tax Expense | C18: =C17*Assumptions!$C$20 -> 86461.25 | D18: =D17*Assumptions!$C$20 -> 80932.5 | E18: =E17*Assumptions!$C$20 -> 80177.5 | F18: =F17*Assumptions!$C$20 -> 78298 | G18: =G17*Assumptions!$C$20 -> 84196.84 | H18: =H17*Assumptions!$C$20 -> 104405.46 | I18: =I17*Assumptions!$C$20 -> 135414.25 | J18: =J17*Assumptions!$C$20 -> 184547.08
B19: Net Income | C19: =C17-C18 -> 259383.75 | D19: =D17-D18 -> 242797.5 | E19: =E17-E18 -> 240532.5 | F19: =F17-F18 -> 234894 | G19: =G17-G18 -> 252590.52 | H19: =H17-H18 -> 313216.38 | I19: =I17-I18 -> 406242.76 | J19: =J17-J18 -> 553641.25
B20: Net Margin % | C20: =IF(C6=0,"-",C19/C6) -> 0.32422969 | D20: =IF(D6=0,"-",D19/D6) -> 0.28564412 | E20: =IF(E6=0,"-",E19/E6) -> 0.26144837 | F20: =IF(F6=0,"-",F19/F6) -> 0.24086751 | G20: =IF(G6=0,"-",G19/G6) -> 0.23982784 | H20: =IF(H6=0,"-",H19/H6) -> 0.26552719 | I20: =IF(I6=0,"-",I19/I6) -> 0.29688768 | J20: =IF(J6=0,"-",J19/J6) -> 0.33164629

Sheet FCF Build
B2: FREE CASH FLOW BUILD
C4: Actuals | F4: Projections
B5: Particulars | C5: 1 | D5: 2 | E5: 3 | F5: 1 | G5: 2 | H5: 3 | I5: 4 | J5: 5
B6: EBIT | C6: ='Income Statement'!C15 -> 347845 | D6: ='Income Statement'!D15 -> 325830 | E6: ='Income Statement'!E15 -> 323010 | F6: ='Income Statement'!F15 -> 315692 | G6: ='Income Statement'!G15 -> 339487.36 | H6: ='Income Statement'!H15 -> 420521.84 | I6: ='Income Statement'!I15 -> 544757.02 | J6: ='Income Statement'!J15 -> 741488.33
B7: Less: Taxes on EBIT | C7: =-(C6*Assumptions!$C$20) -> -86961.25 | D7: =-(D6*Assumptions!$C$20) -> -81457.5 | E7: =-(E6*Assumptions!$C$20) -> -80752.5 | F7: =-(F6*Assumptions!$C$20) -> -78923 | G7: =-(G6*Assumptions!$C$20) -> -84871.84 | H7: =-(H6*Assumptions!$C$20) -> -105130.46 | I7: =-(I6*Assumptions!$C$20) -> -136189.25 | J7: =-(J6*Assumptions!$C$20) -> -185372.08
B8: Net Operating Profit After Tax | C8: =C6+C7 -> 260883.75 | D8: =D6+D7 -> 244372.5 | E8: =E6+E7 -> 242257.5 | F8: =F6+F7 -> 236769 | G8: =G6+G7 -> 254615.52 | H8: =H6+H7 -> 315391.38 | I8: =I6+I7 -> 408567.76 | J8: =J6+J7 -> 556116.25
B9: Add: D&A | C9: ='Income Statement'!C14 -> 32000 | D9: ='Income Statement'!D14 -> 34000 | E9: ='Income Statement'!E14 -> 36800 | F9: ='Income Statement'!F14 -> 39008 | G9: ='Income Statement'!G14 -> 42128.64 | H9: ='Income Statement'!H14 -> 47184.077 | I9: ='Income Statement'!I14 -> 54733.529 | J9: ='Income Statement'!J14 -> 66774.905
B10: Less: Capital Expenditures (CapEx) | C10: -40000 | D10: -45000 | E10: -47000 | F10: =-'Income Statement'!F6*Assumptions!$C$28 -> -48760 | G10: =-'Income Statement'!G6*Assumptions!$C$28 -> -52660.8 | H10: =-'Income Statement'!H6*Assumptions!$C$28 -> -58980.096 | I10: =-'Income Statement'!I6*Assumptions!$C$28 -> -68416.911 | J10: =-'Income Statement'!J6*Assumptions!$C$28 -> -83468.632
B11: Less: Change in Net Working Capital | C11: -15 | D11: -18 | E11: -20 | F11: =-('Income Statement'!F6*(Assumptions!$C$23+Assumptions!$C$24-Assumptions!$C$25)/365-'Income Statement'!E6*(Assumptions!$C$23+Assumptions!$C$24-Assumptions!$C$25)/365) -> -9830.137 | G11: =-('Income Statement'!G6*(Assumptions!$C$23+Assumptions!$C$24-Assumptions!$C$25)/365-'Income Statement'!F6*(Assumptions!$C$23+Assumptions!$C$24-Assumptions!$C$25)/365) -> -13893.26 | H11: =-('Income Statement'!H6*(Assumptions!$C$23+Assumptions!$C$24-Assumptions!$C$25)/365-'Income Statement'!G6*(Assumptions!$C$23+Assumptions!$C$24-Assumptions!$C$25)/365) -> -22507.082 | I11: =-('Income Statement'!I6*(Assumptions!$C$23+Assumptions!$C$24-Assumptions!$C$25)/365-'Income Statement'!H6*(Assumptions!$C$23+Assumptions!$C$24-Assumptions!$C$25)/365) -> -33610.575 | J11: =-('Income Statement'!J6*(Assumptions!$C$23+Assumptions!$C$24-Assumptions!$C$25)/365-'Income Statement'!I6*(Assumptions!$C$23+Assumptions!$C$24-Assumptions!$C$25)/365) -> -53608.868
B12: Free Cash Flow (FCF) | C12: =C8+C9+C10+C11 -> 252868.75 | D12: =D8+D9+D10+D11 -> 233354.5 | E12: =E8+E9+E10+E11 -> 232037.5 | F12: =F8+F9+F10+F11 -> 217186.86 | G12: =G8+G9+G10+G11 -> 230190.1 | H12: =H8+H9+H10+H11 -> 281088.28 | I12: =I8+I9+I10+I11 -> 361273.81 | J12: =J8+J9+J10+J11 -> 485813.65

Sheet DCF Valuation
B2: DCF VALUATION
B4: Particulars | F4: 1 | G4: 2 | H4: 3 | I4: 4 | J4: 5
B5: A. DISCOUNT FACTORS
B6: Discount Period | F6: 1 | G6: =F6+1 -> 2 | H6: =G6+1 -> 3 | I6: =H6+1 -> 4 | J6: =I6+1 -> 5
B7: WACC | F7: =Assumptions!$C$36 -> 0.136 | G7: =Assumptions!$C$36 -> 0.136 | H7: =Assumptions!$C$36 -> 0.136 | I7: =Assumptions!$C$36 -> 0.136 | J7: =Assumptions!$C$36 -> 0.136
B8: Discount Factor [1/(1+WACC)^period] | F8: =1/(1+F7)^F6 -> 0.88028169 | G8: =1/(1+G7)^G6 -> 0.77489585 | H8: =1/(1+H7)^H6 -> 0.68212663 | I8: =1/(1+I7)^I6 -> 0.60046358 | J8: =1/(1+J7)^J6 -> 0.5285771
B9: B. PRESENT VALUE OF FREE CASH FLOWS
B10: FCF | F10: ='FCF Build'!F12 -> 217186.86 | G10: ='FCF Build'!G12 -> 230190.1 | H10: ='FCF Build'!H12 -> 281088.28 | I10: ='FCF Build'!I12 -> 361273.81 | J10: ='FCF Build'!J12 -> 485813.65
B11: PV of FCF | F11: =F10*F8 -> 191185.62 | G11: =G10*G8 -> 178373.35 | H11: =H10*H8 -> 191737.8 | I11: =I10*I8 -> 216931.76 | J11: =J10*J8 -> 256789.97
B12: Sum of PV(FCF) | F12: =SUM(F11:J11) -> 1035018.5
B14: C. TERMINAL VALUE
B15: Terminal Year FCF | F15: ='FCF Build'!J12 -> 485813.65
B16: Terminal Growth Rate (g) | F16: =Assumptions!$C$39 -> 0.025
B17: Gordon Growth TV [FCF*(1+g)/(WACC-g)] | F17: =F15*(1+F16)/(F7-F16) -> 4486117.1
B18: PV of Terminal Value | F18: =F17*J8 -> 2371258.7
B21: Sum of PV(FCF) | F21: =F12 -> 1035018.5
B22: (+) PV of Terminal Value | F22: =F18 -> 2371258.7
B23: DCF Value of the Business | F23: =F21+F22 -> 3406277.3
