Workbook

Sheet Instructions - VC Method
B2: Step-by-Step Instructions
B4: Steps | C4: Details
B5: 1 | C5: Open the “Inputs” sheet and set exit, round, return, and founder assumptions (light yellow cells)
B6: 2 | C6: Review the “VC Method” sheet for the implied pre-money valuation per round
B7: 3 | C7: Check the “Cap Table” for round-by-round ownership and dilution
B8: 4 | C8: See the “Investor Returns” sheet for exit proceeds, MOIC, and IRR
B9: 5 | C9: Read summary KPIs on the “Dashboard”
B12: What Each Input Means
B14: Metric | E14: Description
B15: Projected Revenue at Exit | E15: Forecast revenue at exit, multiplied by the exit multiple.
B16: Revenue Multiple at Exit | E16: Valuation multiple applied to exit revenue to set exit value.
B17: Years to Exit | E17: Time horizon used to discount the exit value back to today.
B18: Required Return / IRR | E18: Target MOIC and IRR investors require, used to discount the exit.
B19: Investment & Pre-Money per round | E19: Round sizes and pre-money valuations for Seed through Series C.
B20: ESOP Pool This Round | E20: Option pool added each round, diluting existing holders.
B23: Important Guidelines
B25: Guideline | E25: Description
B26: Edit light yellow cells only | E26: Blue is input; black is formula, green is a cross-sheet link — don’t overwrite.
B27: Method works backward | E27: Exit value ÷ required return = implied post-money; minus investment = pre-money.
B28: Mind dilution | E28: Future rounds and ESOP top-ups dilute earlier ownership.
B29: Compare to actuals | E29: The verdict flags whether each round is investor- or founder-favoured.

Sheet Cover
B1: VENTURE CAPITAL METHOD Startup Valuation Model
B10: 1 INPUTS
B11: All assumptions — revenue, exit multiples, round sizes, required returns
B13: 2 VC METHOD
B14: Implied pre-money valuation using the VC backward-looking formula
B16: 3 CAP TABLE
B17: Round-by-round ownership: founders, investors, ESOP after each round
B19: 4 INVESTOR RETURNS
B20: Exit proceeds, MOIC and IRR for every investor at the base exit
B23: 5 DASHBOARD
B24: Summary KPIs: IRR, MOIC, ownership, absolute gain, exit snapshot
B27: COLOR LEGEND
... B33: Green — cross-sheet link pulling data from another tab.

Sheet Inputs
B1: INPUTS
B3: COMPANY & EXIT ASSUMPTIONS | E3: ROUND ASSUMPTIONS | F3: Seed | G3: Series A | H3: Series B | I3: Series C
B4: Projected Revenue at Exit ($) | C4: 25000000 | E4: Investment ($) | F4: 1000000 | G4: 5000000 | H4: 15000000 | I4: 40000000
B5: Revenue Multiple at Exit | C5: 8 | E5: Pre-Money Valuation ($) | F5: 5000000 | G5: 20000000 | H5: 60000000 | I5: 180000000
B6: Years to Exit (from today) | C6: 5 | E6: Round Year | F6: 2026 | G6: 2027 | H6: 2029 | I6: 2030
E7: ESOP Pool This Round (%) | F7: 0.1 | G7: 0.05 | H7: 0.03 | I7: 0.02
B8: VC METHOD ASSUMPTIONS
B9: Required Return Multiple (target MOIC) | C9: 10 | E9: INVESTOR RETURN REQUIREMENTS
B10: Required IRR (%) | C10: 0.35 | E10: Required IRR (%) | F10: 0.4 | G10: 0.3 | H10: 0.25 | I10: 0.2
B11: Expected Dilution from Future Rounds | C11: 0.2 | E11: Target MOIC (x) | F11: 10 | G11: 5 | H11: 3 | I11: 2.5
B13: FOUNDERS
B14: Founder 1 Name | C14: Founder 1
B15: Founder 2 Name | C15: Founder 2
B16: Founder 1 Initial Ownership (%) | C16: 0.5
B17: Founder 2 Initial Ownership (%) | C17: 0.5

Sheet VC Method
B1: VC METHOD — Implied Valuation Calculator
B2: The VC Method works backward from a future exit: Exit Value ÷ Required Return = Implied Post-Money. Implied Pre-Money = Implied Post-Money − Investment. Blue = input | Black = formula | Green = cross-sheet link.
B4: METRIC | C4: Seed | D4: Series A | E4: Series B | F4: Series C
B5: STEP 1 — FORECAST THE EXIT VALUE
B6: Exit Revenue ($) | C6: =Inputs!C4 -> 25000000 | D6: =Inputs!C4 -> 25000000 | E6: =Inputs!C4 -> 25000000 | F6: =Inputs!C4 -> 25000000
B7: Exit Multiple | C7: =Inputs!C5 -> 8 | D7: =Inputs!C5 -> 8 | E7: =Inputs!C5 -> 8 | F7: =Inputs!C5 -> 8
B8: Exit Valuation | C8: =C6*C7 -> 200000000 | D8: =D6*D7 -> 200000000 | E8: =E6*E7 -> 200000000 | F8: =F6*F7 -> 200000000
B10: STEP 2 — DISCOUNT BACK TO TODAY
B11: Years to Exit from This Round | C11: =(Inputs!$F$6+Inputs!$C$6)-Inputs!F6 -> 5 | D11: =(Inputs!$F$6+Inputs!$C$6)-Inputs!G6 -> 4 | E11: =(Inputs!$F$6+Inputs!$C$6)-Inputs!H6 -> 2 | F11: =(Inputs!$F$6+Inputs!$C$6)-Inputs!I6 -> 1
B12: Required MOIC | C12: =Inputs!F11 -> 10 | D12: =Inputs!G11 -> 5 | E12: =Inputs!H11 -> 3 | F12: =Inputs!I11 -> 2.5
B13: Required IRR | C13: =Inputs!F10 -> 0.4 | D13: =Inputs!G10 -> 0.3 | E13: =Inputs!H10 -> 0.25 | F13: =Inputs!I10 -> 0.2
B14: Discount Factor | C14: =1/(1+C13)^C11 -> 0.18593443 | D14: =1/(1+D13)^D11 -> 0.3501278 | E14: =1/(1+E13)^E11 -> 0.64 | F14: =1/(1+F13)^F11 -> 0.83333333
B16: STEP 3 — IMPLIED OWNERSHIP REQUIRED
B17: Required Ownership at Entry | C17: =(Inputs!$F$4*C12)/C8 -> 0.05 | D17: =(Inputs!$G$4*D12)/D8 -> 0.125 | E17: =(Inputs!$H$4*E12)/E8 -> 0.225 | F17: =(Inputs!$I$4*F12)/F8 -> 0.5
B18: Dilution-Adjusted Required Ownership | C18: =C17/(1-Inputs!$C$11) -> 0.0625 | D18: =D17/(1-Inputs!$C$11) -> 0.15625 | E18: =E17/(1-Inputs!$C$11) -> 0.28125 | F18: =F17/(1-Inputs!$C$11) -> 0.625
B20: STEP 4 — IMPLIED PRE-MONEY VALUATION
B21: Implied Post-Money Valuation | C21: =Inputs!$F$4/C17 -> 20000000 | D21: =Inputs!$G$4/D17 -> 40000000 | E21: =Inputs!$H$4/E17 -> 66666667 | F21: =Inputs!$I$4/F17 -> 80000000
B22: Implied Pre-Money Valuation | C22: =C21-Inputs!$F$4 -> 19000000 | D22: =D21-Inputs!$G$4 -> 35000000 | E22: =E21-Inputs!$H$4 -> 51666667 | F22: =F21-Inputs!$I$4 -> 40000000
B23: Actual Pre-Money Valuation | C23: =Inputs!$F$5 -> 5000000 | D23: =Inputs!$G$5 -> 20000000 | E23: =Inputs!$H$5 -> 60000000 | F23: =Inputs!$I$5 -> 180000000
B24: VC Method Verdict | C24: =IF(C22>Inputs!$F$5,"Investor favoured","Founder favoured") -> Investor favoured | D24: =IF(D22>Inputs!$G$5,"Investor favoured","Founder favoured") -> Investor favoured | E24: =IF(E22>Inputs!$H$5,"Investor favoured","Founder favoured") -> Founder favoured | F24: =IF(F22>Inputs!$I$5,"Investor favoured","Founder favoured") -> Founder favoured
B25: Gap: Actual vs VC-Implied Pre-Money | C25: =Inputs!$F$5-C22 -> -14000000 | D25: =Inputs!$G$5-D22 -> -15000000 | E25: =Inputs!$H$5-E22 -> 8333333.3 | F25: =Inputs!$I$5-F22 -> 140000000

Sheet Cap Table
B1: CAP TABLE — Fully-Diluted Ownership at Each Round
B2: Ownership % of fully-diluted share count. Each round: new investor % + ESOP top-up dilutes all prior holders proportionally.
B4: STAKEHOLDER | C4: Pre-Seed (Today) | D4: Post-Seed | E4: Post-Ser A | F4: Post-Ser B | G4: Post-Ser C
B5: Founder 1 | C5: =Inputs!C16 -> 0.5 | D5: =C5*(1-Inputs!$F$4/(Inputs!$F$4+Inputs!$F$5)-Inputs!$F$7) -> 0.36666667 | E5: =D5*(1-Inputs!$G$4/(Inputs!$G$4+Inputs!$G$5)-Inputs!$G$7) -> 0.275 | F5: =E5*(1-Inputs!$H$4/(Inputs!$H$4+Inputs!$H$5)-Inputs!$H$7) -> 0.21175 | G5: =F5*(1-Inputs!$I$4/(Inputs!$I$4+Inputs!$I$5)-Inputs!$I$7) -> 0.169015
B6: Founder 2 | C6: =Inputs!C17 -> 0.5 | D6: =C6*(1-Inputs!$F$4/(Inputs!$F$4+Inputs!$F$5)-Inputs!$F$7) -> 0.36666667 | E6: =D6*(1-Inputs!$G$4/(Inputs!$G$4+Inputs!$G$5)-Inputs!$G$7) -> 0.275 | F6: =E6*(1-Inputs!$H$4/(Inputs!$H$4+Inputs!$H$5)-Inputs!$H$7) -> 0.21175 | G6: =F6*(1-Inputs!$I$4/(Inputs!$I$4+Inputs!$I$5)-Inputs!$I$7) -> 0.169015
B7: Seed Investors | C7: 0 | D7: =Inputs!$F$4/(Inputs!$F$4+Inputs!$F$5) -> 0.16666667 | E7: =D7*(1-Inputs!$G$4/(Inputs!$G$4+Inputs!$G$5)-Inputs!$G$7) -> 0.125 | F7: =E7*(1-Inputs!$H$4/(Inputs!$H$4+Inputs!$H$5)-Inputs!$H$7) -> 0.09625 | G7: =F7*(1-Inputs!$I$4/(Inputs!$I$4+Inputs!$I$5)-Inputs!$I$7) -> 0.076825
B8: Series A Investors | C8: 0 | D8: 0 | E8: =Inputs!$G$4/(Inputs!$G$4+Inputs!$G$5) -> 0.2 | F8: =E8*(1-Inputs!$H$4/(Inputs!$H$4+Inputs!$H$5)-Inputs!$H$7) -> 0.154 | G8: =F8*(1-Inputs!$I$4/(Inputs!$I$4+Inputs!$I$5)-Inputs!$I$7) -> 0.12292
B9: Series B Investors | C9: 0 | D9: 0 | E9: 0 | F9: =Inputs!$H$4/(Inputs!$H$4+Inputs!$H$5) -> 0.2 | G9: =F9*(1-Inputs!$I$4/(Inputs!$I$4+Inputs!$I$5)-Inputs!$I$7) -> 0.15963636
B10: Series C Investors | C10: 0 | D10: 0 | E10: 0 | F10: 0 | G10: =Inputs!$I$4/(Inputs!$I$4+Inputs!$I$5) -> 0.18181818
B11: ESOP Pool | C11: 0 | D11: =Inputs!$F$7 -> 0.1 | E11: =D11*(1-Inputs!$G$4/(Inputs!$G$4+Inputs!$G$5))+Inputs!$G$7 -> 0.13 | F11: =E11*(1-Inputs!$H$4/(Inputs!$H$4+Inputs!$H$5))+Inputs!$H$7 -> 0.134 | G11: =F11*(1-Inputs!$I$4/(Inputs!$I$4+Inputs!$I$5))+Inputs!$I$7 -> 0.12963636
B13: TOTAL | C13: =SUM(C5:C11) -> 1 | D13: =SUM(D5:D11) -> 1 | E13: =SUM(E5:E11) -> 1.005 | F13: =SUM(F5:F11) -> 1.00775 | G13: =SUM(G5:G11) -> 1.0088659
B15: Combined Founder Ownership | C15: =C5+C6 -> 1 | D15: =D5+D6 -> 0.73333333 | E15: =E5+E6 -> 0.55 | F15: =F5+F6 -> 0.4235 | G15: =G5+G6 -> 0.33803

Sheet Investor Returns
B1: INVESTOR RETURNS — Base Exit Scenario
B2: Exit proceeds = investor ownership at exit × exit valuation (base). MOIC = proceeds ÷ investment. IRR = MOIC^(1÷years)−1.
B4: Investor | C4: Ownership at Exit (%) | D4: Investment ($) | E4: Entry Year | F4: Years Held | G4: Exit Proceeds ($) | H4: MOIC (x) | I4: IRR (%)
B5: Seed | C5: ='Cap Table'!G7 -> 0.076825 | D5: =Inputs!$F$4 -> 1000000 | E5: =Inputs!$F$6 -> 2026 | F5: =(Inputs!$F$6+Inputs!$C$6)-E5 -> 5 | G5: =C5*Inputs!$C$4*Inputs!$C$5 -> 15365000 | H5: =IFERROR(G5/D5,0) -> 15.365 | I5: =IFERROR((G5/D5)^(1/F5)-1,0) -> 0.72705637
B6: Series A | C6: ='Cap Table'!G8 -> 0.12292 | D6: =Inputs!$G$4 -> 5000000 | E6: =Inputs!$G$6 -> 2027 | F6: =(Inputs!$F$6+Inputs!$C$6)-E6 -> 4 | G6: =C6*Inputs!$C$4*Inputs!$C$5 -> 24584000 | H6: =IFERROR(G6/D6,0) -> 4.9168 | I6: =IFERROR((G6/D6)^(1/F6)-1,0) -> 0.48908893
B7: Series B | C7: ='Cap Table'!G9 -> 0.15963636 | D7: =Inputs!$H$4 -> 15000000 | E7: =Inputs!$H$6 -> 2029 | F7: =(Inputs!$F$6+Inputs!$C$6)-E7 -> 2 | G7: =C7*Inputs!$C$4*Inputs!$C$5 -> 31927273 | H7: =IFERROR(G7/D7,0) -> 2.1284848 | I7: =IFERROR((G7/D7)^(1/F7)-1,0) -> 0.45893278
B8: Series C | C8: ='Cap Table'!G10 -> 0.18181818 | D8: =Inputs!$I$4 -> 40000000 | E8: =Inputs!$I$6 -> 2030 | F8: =(Inputs!$F$6+Inputs!$C$6)-E8 -> 1 | G8: =C8*Inputs!$C$4*Inputs!$C$5 -> 36363636 | H8: =IFERROR(G8/D8,0) -> 0.90909091 | I8: =IFERROR((G8/D8)^(1/F8)-1,0) -> -0.090909091
B10: TOTAL | D10: =SUM(D5:D8) -> 61000000 | G10: =SUM(G5:G8) -> 1.0823991e+08 | H10: =IFERROR(G10/D10,0) -> 1.7744247

Sheet Dashboard
B1: VENTURE CAPITAL METHOD — DASHBOARD
B3: Target IRR (Seed) | D3: Absolute Gain ($) (Total) | F3: Blended MOIC | H3: Founder Ownership at Exit | J3: Exit Valuation (Base, $)
B4: ='Investor Returns'!I5 -> 0.72705637 | D4: ='Investor Returns'!G10-'Investor Returns'!D10 -> 47239909 | F4: ='Investor Returns'!H10 -> 1.7744247 | H4: ='Cap Table'!G15 -> 0.33803 | J4: =Inputs!$C$4*Inputs!$C$5 -> 200000000
B7: ROUND SUMMARY
C8: Seed | D8: Series A | E8: Series B | F8: Series C
B9: Investment ($) | C9: =Inputs!$F$4 -> 1000000 | D9: =Inputs!$G$4 -> 5000000 | E9: =Inputs!$H$4 -> 15000000 | F9: =Inputs!$I$4 -> 40000000
B10: Pre-Money ($) | C10: =Inputs!$F$5 -> 5000000 | D10: =Inputs!$G$5 -> 20000000 | E10: =Inputs!$H$5 -> 60000000 | F10: =Inputs!$I$5 -> 180000000
B11: Post-Money ($) | C11: =Inputs!$F$4+Inputs!$F$5 -> 6000000 | D11: =Inputs!$G$4+Inputs!$G$5 -> 25000000 | E11: =Inputs!$H$4+Inputs!$H$5 -> 75000000 | F11: =Inputs!$I$4+Inputs!$I$5 -> 220000000
B12: Investor Ownership % (entry) | C12: =Inputs!$F$4/(Inputs!$F$4+Inputs!$F$5) -> 0.16666667 | D12: =Inputs!$G$4/(Inputs!$G$4+Inputs!$G$5) -> 0.2 | E12: =Inputs!$H$4/(Inputs!$H$4+Inputs!$H$5) -> 0.2 | F12: =Inputs!$I$4/(Inputs!$I$4+Inputs!$I$5) -> 0.18181818
B13: Exit Proceeds ($) | C13: ='Investor Returns'!G5 -> 15365000 | D13: ='Investor Returns'!G6 -> 24584000 | E13: ='Investor Returns'!G7 -> 31927273 | F13: ='Investor Returns'!G8 -> 36363636
B14: MOIC (x) | C14: ='Investor Returns'!H5 -> 15.365 | D14: ='Investor Returns'!H6 -> 4.9168 | E14: ='Investor Returns'!H7 -> 2.1284848 | F14: ='Investor Returns'!H8 -> 0.90909091
B17: MOIC BY INVESTOR
B18: Investor | C18: Seed | D18: Series A | E18: Series B | F18: Series C
B19: MOIC (x) | C19: ='Investor Returns'!H5 -> 15.365 | D19: ='Investor Returns'!H6 -> 4.9168 | E19: ='Investor Returns'!H7 -> 2.1284848 | F19: ='Investor Returns'!H8 -> 0.90909091
